[
  {
    "platform": "tiktok",
    "account": "bpatomedia",
    "url": "https://www.tiktok.com/@bpatomedia/video/7654282989702008077",
    "thumbnail": "https://p19-common-sign.tiktokcdn-us.com/tos-useast5-p-0068-tx/okCqNmnMyAS3DRFqgQFqO8SDOfL2OeXEDEBRyQ~tplv-tiktokx-cropcenter:500:800.jpeg?biz_tag=musically_video.video_cover&dr=9638&idc=useast5&ps=13740610&refresh_token=ffd97e74&shcp=9b759fb9&shp=c1333099&t=4d5b0474&x-expires=1783976400&x-signature=WIb0v6hDmSH%2BvGG%2FP3dkORZR2%2FY%3D",
    "video": "https://v16m.tiktokcdn-us.com/e6a257dc57a3486564342b0961faea10/6a5558d8/video/tos/useast5/tos-useast5-pve-0068-tx/o05RDEgMQCqgOXEeIByo2SFGLOq98DfX3dAonO/?a=1233&bti=NEBzNTY6QGo6OjZALnAjNDQuYCMxNDNg&&bt=4351&ft=gKfIn8s6oA-O12NvgPZZzIxRW-jyO3_45SY&mime_type=video_mp4&rc=Z2Y7PDs8ODw5NWk7NWlnM0BpanVya3U5cm1xOzMzZzczNEAuLTRjLjVjX2ExNjA0MTFgYSNeYmBkMmRrZ3BhLS1kMS9zcw%3D%3D&vvpl=1&l=202607131529544A102FF5115A2A0AEC78&btag=e000b0000",
    "carousel_urls": [],
    "format": "TikTok",
    "caption": "Ocean blue \ud83d\udca7 #Lifestyle #travel #adventure #cinematic #hawaii",
    "timestamp": "2026-06-22T18:07:28+00:00",
    "likes": 92680,
    "comments": 72,
    "shares": 8239,
    "views": 324739,
    "saves": 9872,
    "music": "original sound - bpatomedia",
    "audio_song": "original sound - bpatomedia",
    "audio_artist": "Bpato Media",
    "audio_id": "7654283007238474509",
    "audio_is_original": true,
    "engagement": 100991,
    "trendScore": 31.1,
    "velocity": 15544,
    "ageDays": 20.9,
    "source": "keyword:cinematic travel",
    "isNewAccount": true
  },
  {
    "platform": "tiktok",
    "account": "darryltengg",
    "url": "https://www.tiktok.com/@darryltengg/video/7656448364464114965",
    "thumbnail": "https://p16-common-sign.tiktokcdn-us.com/tos-alisg-p-0037/oUPASirIBAABi6PbXhEzBaYKD1AkEwAnGBZEJ~tplv-tiktokx-cropcenter:500:800.jpeg?biz_tag=musically_video.video_cover&dr=9638&idc=useast5&ps=13740610&refresh_token=b0fdc4cf&shcp=9b759fb9&shp=c1333099&t=4d5b0474&x-expires=1783976400&x-signature=epHWW0V8p3lhCvbgtj8RsZpepAg%3D",
    "video": "https://v16m.tiktokcdn-us.com/d1064022e89ef8a9409bf67d89c8672e/6a5558e4/video/tos/alisg/tos-alisg-pve-0037c001/oMBB67A4iAqxEyykBYW3aYKiIQRB0ZwDvXEEE/?a=1233&bti=NEBzNTY6QGo6OjZALnAjNDQuYCMxNDNg&&bt=475&ft=gKfIn8s6oA-O12NvgPZZzIxRW-jyO3_45SY&mime_type=video_mp4&rc=ODs2Z2YzPDM7OWY1NjNkOEBpM3JpZmw5cnVsPDMzODczNEA1MzBhYjI0XjIxXzFeLjMuYSNxZGRsMmRraS1hLS1kMWBzcw%3D%3D&vvpl=1&l=202607131529544A102FF5115A2A0AEC78&btag=e000b8000",
    "carousel_urls": [],
    "format": "TikTok",
    "caption": "my favourite model  @amandahanyq  IB @Sax Napat  #sony #film #travel #cinematic",
    "timestamp": "2026-06-28T14:10:05+00:00",
    "likes": 227218,
    "comments": 292,
    "shares": 91013,
    "views": 1040705,
    "saves": 12527,
    "music": "original sound - josuegomeza",
    "audio_song": "original sound - josuegomeza",
    "audio_artist": "Josuegomeza",
    "audio_id": "7612667609577835277",
    "audio_is_original": true,
    "engagement": 318523,
    "trendScore": 30.6,
    "velocity": 69124,
    "ageDays": 15.1,
    "source": "keyword:cinematic travel",
    "isNewAccount": true
  },
  {
    "platform": "tiktok",
    "account": "ericklj.film",
    "url": "https://www.tiktok.com/@ericklj.film/video/7657649905221143815",
    "thumbnail": "https://p19-common-sign.tiktokcdn-us.com/tos-alisg-p-0037/oIwbeAGkefCDILjnUC0dkA4IAIlQES6QAA5PIM~tplv-tiktokx-cropcenter:500:800.jpeg?biz_tag=musically_video.video_cover&dr=9638&idc=useast5&ps=13740610&refresh_token=287a3d38&shcp=9b759fb9&shp=c1333099&t=4d5b0474&x-expires=1783976400&x-signature=o%2BH%2B5WoOOEqnchBeBF2XagEJbgo%3D",
    "video": "https://v45.tiktokcdn-us.com/e483137006e75be1cba76a97d4032c98/6a55590f/video/tos/alisg/tos-alisg-pve-0037c001/oUEYiLiEIAw1EaIficiuF0RgYDg4LCA3BArIQz/?a=1233&bti=NEBzNTY6QGo6OjZALnAjNDQuYCMxNDNg&&bt=831&ft=aEKfuqT0mI2PD125QqqI3wUThrlcMeF~O5&mime_type=video_mp4&rc=ZzYzNzQzZGY5OGdmZ2kzN0BpMzU1cm05cjVxPDMzODczNEBfYDI1MTNeNTExYjU1YjUyYSNgLmtvMmRjLS9hLS1kMWBzcw%3D%3D&vvpl=1&l=20260713153011635B46952589FA099C73&btag=e0008d000",
    "carousel_urls": [],
    "format": "TikTok",
    "caption": "Oaxaca y t\u00fa gente, que bonitos fueron.  . #oaxaca #oaxacamexico #guelaguetza  #oaxacatravel #filmmaking",
    "timestamp": "2026-07-01T19:52:49+00:00",
    "likes": 7136,
    "comments": 65,
    "shares": 577,
    "views": 27269,
    "saves": 872,
    "music": "La Cumbia Del Mole",
    "audio_song": "La Cumbia Del Mole",
    "audio_artist": "Lila Downs",
    "audio_id": "6941876023529048066",
    "audio_is_original": false,
    "engagement": 7778,
    "trendScore": 28.5,
    "velocity": 2307,
    "ageDays": 11.8,
    "source": "keyword:travel filmmaker",
    "isNewAccount": true
  },
  {
    "platform": "tiktok",
    "account": "abby.ccrawford",
    "url": "https://www.tiktok.com/@abby.ccrawford/video/7660657462156037390",
    "thumbnail": "https://p16-common-sign.tiktokcdn-us.com/tos-useast5-p-0068-tx/oMC9ISEDAmfDRmcAPqBgEsSQtAFjFRAUQrCYeg~tplv-tiktokx-cropcenter:500:800.jpeg?biz_tag=musically_video.video_cover&dr=9638&idc=useast5&ps=13740610&refresh_token=84d62441&shcp=9b759fb9&shp=c1333099&t=4d5b0474&x-expires=1783976400&x-signature=HoCmcSEvPQHFBCAJ%2BjpaqOeS5aw%3D",
    "video": "https://v16m.tiktokcdn-us.com/ed765e5124a1656cde8f38cdf3517c52/6a555916/video/tos/useast5/tos-useast5-ve-0068c004-tx/oQHpFA7fgbhsEKfA6AfBQSplGWX9YOBBR4fEhI/?a=1233&bti=NEBzNTY6QGo6OjZALnAjNDQuYCMxNDNg&&bt=1011&ft=gKfIn8buoTfR12NvHPZZzIxRl7PhZQ_45SY&mime_type=video_mp4&rc=PGloNGQ3MzhoNTc1ODU7OEBpamx5PGo5cnM0PDMzZzczNEBhYmBgMTY0NjExMTBjLzAzYSMvNV8wMmRrbjVhLS1kMS9zcw%3D%3D&vvpl=1&l=202607131529572C479AB591AA160A8B01&btag=e00090000",
    "carousel_urls": [],
    "format": "TikTok",
    "caption": "Hiking in the Dolomites causes for a nice big music video\ud83c\udfd4\ufe0f\ud83e\udd7e #backpacking #travel #touchthesky #musicvideo",
    "timestamp": "2026-07-09T22:23:40+00:00",
    "likes": 200903,
    "comments": 229,
    "shares": 13590,
    "views": 756891,
    "saves": 11717,
    "music": "original sound - abby.ccrawford",
    "audio_song": "original sound - abby.ccrawford",
    "audio_artist": "Abby Crawford\ud83e\udeb7",
    "audio_id": "7660657504879151886",
    "audio_is_original": true,
    "engagement": 214722,
    "trendScore": 28.4,
    "velocity": 203867,
    "ageDays": 3.7,
    "source": "keyword:travel film",
    "isNewAccount": true
  },
  {
    "platform": "tiktok",
    "account": "samkyukam",
    "url": "https://www.tiktok.com/@samkyukam/video/7660580749443108127",
    "thumbnail": "https://p19-common-sign.tiktokcdn-us.com/tos-useast8-p-0068-tx2/o49EbWqIP1SDABz2ArVa9fEQFEARJKTezM1PZI~tplv-tiktokx-cropcenter:500:800.jpeg?biz_tag=musically_video.video_cover&dr=9638&idc=useast8&ps=13740610&refresh_token=d88526e4&shcp=9b759fb9&shp=c1333099&t=4d5b0474&x-expires=1783976400&x-signature=m3Gj3Y%2BS%2BcJOBBRVK6H93NrjU6w%3D",
    "video": "https://v16m.tiktokcdn-us.com/dee16af4d33daedbdfdff49a8aa38f30/6a55590d/video/tos/useast8/tos-useast8-pve-0068-tx2/ogtz29MPDEVcMPeWA1FQV1RrSBfrqDEIEVA1ET/?a=1233&bti=NTY6QGo0QHM6OjZANDQuYCMucCMxNDNg&&bt=687&ft=gKfIn8QLodzR12NvkwZZzIxRMQz_XF_45SY&mime_type=video_mp4&rc=ZDQ4Njk8Mzg8OztlNmU5NkBpM2xpd3g5cmR3PDMzaTczNEAtNWFjNjU2NTExX14yLzEwYSMzXmI0MmRzXzRhLS1kMTJzcw%3D%3D&vvpl=1&l=20260713153008E95C0398557BBB07FC19&btag=e00088000",
    "carousel_urls": [],
    "format": "TikTok",
    "caption": "all you need to do is start #smallcreator #film #filmmaking #cinematic",
    "timestamp": "2026-07-09T17:25:58+00:00",
    "likes": 77979,
    "comments": 395,
    "shares": 2290,
    "views": 285024,
    "saves": 11287,
    "music": "original sound - samkyukam",
    "audio_song": "original sound - samkyukam",
    "audio_artist": "samkam",
    "audio_id": "7660580734331046687",
    "audio_is_original": true,
    "engagement": 80664,
    "trendScore": 28.3,
    "velocity": 72721,
    "ageDays": 3.9,
    "source": "keyword:cinematic photography",
    "isNewAccount": true
  },
  {
    "platform": "tiktok",
    "account": "conor.jpg_",
    "url": "https://www.tiktok.com/@conor.jpg_/video/7656886245502618902",
    "thumbnail": "https://p16-common-sign.tiktokcdn-us.com/tos-no1a-p-0037-no/ocBINueYEeCIIchFyCGGeLZjMDALAAXAAg6UId~tplv-tiktokx-cropcenter:500:800.jpeg?biz_tag=musically_video.video_cover&dr=9638&idc=useast5&ps=13740610&refresh_token=eb8ec223&shcp=9b759fb9&shp=c1333099&t=4d5b0474&x-expires=1783976400&x-signature=FCNNjsDhI8KEV5jjqMJl4UFVf6o%3D",
    "video": "https://v19.tiktokcdn-us.com/ace1740c2bdf9c6203f44e47a2cf8377/6a5558e0/video/tos/no1a/tos-no1a-ve-0068-no/ogSIvTYQEia4BWiL4WB7BEYKuBJVZkv1FACZk/?a=1233&bti=NEBzNTY6QGo6OjZALnAjNDQuYCMxNDNg&&bt=1081&ft=gKfIn8buoTfR12NvHPZZzIxRl7PhZQ_45SY&mime_type=video_mp4&rc=OWQ0ODU4OGdmOWRnNDo0ZEBpM3BmaHI5cjxlPDMzbzczNUAtX2M0NGNhXjQxNGAuYTIxYSNfam5mMmRrZC5hLS1kMTFzcw%3D%3D&vvpl=1&l=202607131529572C479AB591AA160A8B01&btag=e000b0000",
    "carousel_urls": [],
    "format": "TikTok",
    "caption": "What if you and me just travel while we can? \ud83c\udfd4\ufe0f\ud83c\udf0a\ud83d\udcf8 #travel #cinematic #filmmaker #hopecore #freedom",
    "timestamp": "2026-06-29T18:29:22+00:00",
    "likes": 12600,
    "comments": 16,
    "shares": 4260,
    "views": 59667,
    "saves": 1409,
    "music": "original sound - conor.jpg_",
    "audio_song": "original sound - conor.jpg_",
    "audio_artist": "Conor | Film & Photography",
    "audio_id": "7656886259482135319",
    "audio_is_original": true,
    "engagement": 16876,
    "trendScore": 28.3,
    "velocity": 4300,
    "ageDays": 13.9,
    "source": "keyword:travel film",
    "isNewAccount": true
  },
  {
    "platform": "tiktok",
    "account": "josiahlebante14",
    "url": "https://www.tiktok.com/@josiahlebante14/video/7656048941351357716",
    "thumbnail": "https://p16-common-sign.tiktokcdn-us.com/tos-alisg-p-0037/oIMlARvT5xfQiaWN1CAAamAg2fA8ozLeAHfhfM~tplv-tiktokx-cropcenter:500:800.jpeg?biz_tag=musically_video.video_cover&dr=9638&idc=useast5&ps=13740610&refresh_token=3c63b3c0&shcp=9b759fb9&shp=c1333099&t=4d5b0474&x-expires=1783976400&x-signature=puNiTcpLh4HYwFGETJw8PZ55J6M%3D",
    "video": "https://v16m.tiktokcdn-us.com/4e82d1a52cc38db78418df7e30894d6b/6a5558fb/video/tos/alisg/tos-alisg-pve-0037c001/owG73PIIQGAoZKfeewLwfZRGsA8NaRAqGF3Ggk/?a=1233&bti=NEBzNTY6QGo6OjZALnAjNDQuYCMxNDNg&&bt=676&ft=gKfIn8s6oA-O12NvgPZZzIxRW-jyO3_45SY&mime_type=video_mp4&rc=Zzc2O2k8ODxkNGZkNDo4NkBpM3V0ZXM5cjZ1OzMzODczNEA1NjZeMWJgNTExNjJjYjZjYSNvM2wyMmQ0c3NhLS1kMWBzcw%3D%3D&vvpl=1&l=202607131529544A102FF5115A2A0AEC78&btag=e00088000",
    "carousel_urls": [],
    "format": "TikTok",
    "caption": "Grateful to call this place Home.\ud83c\udf34 #palawan #palawanboy #cinematic #travel #fyp",
    "timestamp": "2026-06-27T12:20:10+00:00",
    "likes": 47296,
    "comments": 341,
    "shares": 21896,
    "views": 249639,
    "saves": 2948,
    "music": "original sound - josiahlebante14",
    "audio_song": "original sound - josiahlebante14",
    "audio_artist": "Josiah Lebante",
    "audio_id": "7656049006993132309",
    "audio_is_original": true,
    "engagement": 69533,
    "trendScore": 27.9,
    "velocity": 15475,
    "ageDays": 16.1,
    "source": "keyword:cinematic travel",
    "isNewAccount": true
  },
  {
    "platform": "tiktok",
    "account": "syafm___",
    "url": "https://www.tiktok.com/@syafm___/video/7656898353564765471",
    "thumbnail": "https://p19-common-sign.tiktokcdn-us.com/tos-useast8-p-0068-tx2/ogpFjUAfhCLIIhZkIAQAHkaeRZAAeLIGAAqEIY~tplv-tiktokx-cropcenter:500:800.jpeg?biz_tag=musically_video.video_cover&dr=9638&idc=useast8&ps=13740610&refresh_token=c368e755&shcp=9b759fb9&shp=c1333099&t=4d5b0474&x-expires=1783976400&x-signature=OTH9L4XSlcDMTRFWr5YvDO%2Bk59w%3D",
    "video": "https://v16m.tiktokcdn-us.com/1c2065e5ed42b6be7cee0c4de1d11821/6a555900/video/tos/useast8/tos-useast8-ve-0068c004-tx2/okIlCqJEMBsBIARqevEApFEEKxDguQQycfaOJV/?a=1233&bti=NEBzNTY6QGo6OjZALnAjNDQuYCMxNDNg&&bt=417&ft=gKfIn8QLodzR12NvkwZZzIxRMQz_XF_45SY&mime_type=video_mp4&rc=PGdnNTk5N2c5NDc2Ozw7PEBpM2h2ZHg5cjZmPDMzaTczNEAyMjYvNi0xNjExMTEtMmM0YSNhZ2liMmRrMi5hLS1kMTJzcw%3D%3D&vvpl=1&l=20260713153008E95C0398557BBB07FC19&btag=e00088000",
    "carousel_urls": [],
    "format": "TikTok",
    "caption": "#cinematic #colorgrading #sonyzve10 #contentcreation #fyp",
    "timestamp": "2026-06-29T19:16:30+00:00",
    "likes": 352148,
    "comments": 1844,
    "shares": 9117,
    "views": 1408189,
    "saves": 42463,
    "music": "original sound - djrastaroot",
    "audio_song": "original sound - djrastaroot",
    "audio_artist": "Dj Rasta Root",
    "audio_id": "7640151895948610317",
    "audio_is_original": true,
    "engagement": 363109,
    "trendScore": 25.8,
    "velocity": 101728,
    "ageDays": 13.8,
    "source": "keyword:cinematic photography",
    "isNewAccount": true
  },
  {
    "platform": "tiktok",
    "account": "julescinefilms",
    "url": "https://www.tiktok.com/@julescinefilms/video/7660212030154067232",
    "thumbnail": "https://p19-common-sign.tiktokcdn-us.com/tos-useast2a-p-0037-euttp/oUuFJGHgUKGMbaOdDqLIgQGlInAjeECQQfeXMR~tplv-tiktokx-cropcenter:500:800.jpeg?biz_tag=musically_video.video_cover&dr=9638&idc=useast5&ps=13740610&refresh_token=a4e4199f&shcp=9b759fb9&shp=c1333099&t=4d5b0474&x-expires=1783976400&x-signature=R0KF0tn%2BWxKFAOwJmZ0QjYU5%2B6Y%3D",
    "video": "https://v16m.tiktokcdn-us.com/49ecaf67cb184905c2f22351598313c6/6a5558f3/video/tos/useast2a/tos-useast2a-ve-0068-euttp/osaQB3kB63BwikzIBKOvHg6QELiEAvi0yZtE3/?a=1233&bti=NEBzNTY6QGo6OjZALnAjNDQuYCMxNDNg&&bt=995&ft=aEKfuqT0mI2PD125QqqI3wUThrlcMeF~O5&mime_type=video_mp4&rc=ZzkzaThlZTY6OzY0PGU3PEBpM2d2d3Q5cjc7PDMzZjczNUAxYjExLTQzXjExNDIuYDAvYSM1a2xrMmRraDRhLS1kMTNzcw%3D%3D&vvpl=1&l=20260713153011635B46952589FA099C73&btag=e000b8000",
    "carousel_urls": [],
    "format": "TikTok",
    "caption": "nothing else!!\ud83c\udf1e #cinematic #filmmaking",
    "timestamp": "2026-07-08T17:35:01+00:00",
    "likes": 29901,
    "comments": 11,
    "shares": 2447,
    "views": 130989,
    "saves": 1786,
    "music": "Down Under (do you come from a land down under)",
    "audio_song": "Down Under (do you come from a land down under)",
    "audio_artist": "Men At Work",
    "audio_id": "7059773040325822465",
    "audio_is_original": false,
    "engagement": 32359,
    "trendScore": 24.7,
    "velocity": 26661,
    "ageDays": 4.9,
    "source": "keyword:travel filmmaker",
    "isNewAccount": true
  },
  {
    "platform": "tiktok",
    "account": "sedyyfilms",
    "url": "https://www.tiktok.com/@sedyyfilms/video/7659050116015312150",
    "thumbnail": "https://p19-common-sign.tiktokcdn-us.com/tos-no1a-p-0037-no/oIAAdGaABiIwBSLKBaBsYpPrhEwkApKHBi9Ej~tplv-tiktokx-cropcenter:500:800.jpeg?biz_tag=musically_video.video_cover&dr=9638&idc=useast5&ps=13740610&refresh_token=081d90ff&shcp=9b759fb9&shp=c1333099&t=4d5b0474&x-expires=1783976400&x-signature=9BM6uL2z4XOBm%2B8r5GYMGp4jHW4%3D",
    "video": "https://v16m.tiktokcdn-us.com/9aba0a56e2bd9a3a692d50283a57ac3e/6a5558e5/video/tos/no1a/tos-no1a-ve-0068c001-no/oYfeKd5AFQBESLga6LDVkqEZSIDlbaRumFIE9U/?a=1233&bti=NEBzNTY6QGo6OjZALnAjNDQuYCMxNDNg&&bt=1359&ft=gKfIn8s6oA-O12NvgPZZzIxRW-jyO3_45SY&mime_type=video_mp4&rc=aDNnPDpnNTs6N2lmNmllZ0BpM29ybHc5cng5PDMzbzczNUBhLmIyNDJhXzIxM180LTExYSMxamczMmRjZjJhLS1kMTFzcw%3D%3D&vvpl=1&l=202607131529544A102FF5115A2A0AEC78&btag=e000b8000",
    "carousel_urls": [],
    "format": "TikTok",
    "caption": "america\u2019s 250th birthday #newyork #fireworks #cinematic #travel #Lifestyle",
    "timestamp": "2026-07-05T14:26:20+00:00",
    "likes": 15361,
    "comments": 106,
    "shares": 3184,
    "views": 76900,
    "saves": 18372,
    "music": "original sound - sedyyfilms",
    "audio_song": "original sound - sedyyfilms",
    "audio_artist": "SedyyFilms",
    "audio_id": "7659050153264876310",
    "audio_is_original": true,
    "engagement": 18651,
    "trendScore": 24.3,
    "velocity": 9559,
    "ageDays": 8.0,
    "source": "keyword:cinematic travel",
    "isNewAccount": false
  },
  {
    "platform": "tiktok",
    "account": "henbuu",
    "url": "https://www.tiktok.com/@henbuu/video/7658275563496459534",
    "thumbnail": "https://p19-common-sign.tiktokcdn-us.com/tos-useast5-p-0068-tx/ogglXE6SqD9hqqL6ADBqh2DRFDjISIfRUEheHp~tplv-tiktokx-cropcenter:500:800.jpeg?biz_tag=musically_video.video_cover&dr=9638&idc=useast5&ps=13740610&refresh_token=76855b06&shcp=9b759fb9&shp=c1333099&t=4d5b0474&x-expires=1783976400&x-signature=cUVSwABNOReuRQuezV14DXMkQx4%3D",
    "video": "https://v19.tiktokcdn-us.com/02a11c10b2fedcb92b9d6231c79f8a4b/6a5558e1/video/tos/useast5/tos-useast5-pve-0068-tx/oUL6VXgYSEbYeChqApQBEqIHfjE1VBDSqD6RRF/?a=1233&bti=NEBzNTY6QGo6OjZALnAjNDQuYCMxNDNg&&bt=1277&ft=gKfIn8s6oA-O12NvgPZZzIxRW-jyO3_45SY&mime_type=video_mp4&rc=ZWk6OGU3NjtoaTgzOWRnM0BpamQ8O3c5cmx0PDMzZzczNEA0MmEuMV9gNTMxMl9fNmJgYSNoY15jMmRzZTBhLS1kMS9zcw%3D%3D&vvpl=1&l=202607131529544A102FF5115A2A0AEC78&btag=e000b8000",
    "carousel_urls": [],
    "format": "TikTok",
    "caption": "Visual diaries ep.9 No better feeling than exploring somewhere new with a camera in hand, chasing light, and capturing all the little moments along the way \ud83d\udcf8\u2728 Shot on Sony and color graded with my cinematic SLOG3 LUTs, check out the link in bio if you want to get similar colors with a few clicks \ud83c\udfa8 Happy creating friends :) #filmmaker #cinematic #fyp #travel",
    "timestamp": "2026-07-03T12:21:23+00:00",
    "likes": 36568,
    "comments": 50,
    "shares": 9943,
    "views": 193423,
    "saves": 3932,
    "music": "original sound - henbuu",
    "audio_song": "original sound - henbuu",
    "audio_artist": "Henbu",
    "audio_id": "7658275788659100430",
    "audio_is_original": true,
    "engagement": 46561,
    "trendScore": 24.1,
    "velocity": 19092,
    "ageDays": 10.1,
    "source": "keyword:cinematic travel",
    "isNewAccount": true
  },
  {
    "platform": "tiktok",
    "account": "andreividanes",
    "url": "https://www.tiktok.com/@andreividanes/video/7655236116563414279",
    "thumbnail": "https://p19-common-sign.tiktokcdn-us.com/tos-alisg-p-0037/ocz4I4feAhCGAg0vosgTPtLfRcGzQbecFFXMGo~tplv-tiktokx-cropcenter:500:800.jpeg?biz_tag=musically_video.video_cover&dr=9638&idc=useast5&ps=13740610&refresh_token=55dea0bd&shcp=9b759fb9&shp=c1333099&t=4d5b0474&x-expires=1783976400&x-signature=lR%2Fjb2ND7bw5LJ5P46J1grKHKNY%3D",
    "video": "https://v16m.tiktokcdn-us.com/2771484423e5eb57032d509a99d57eab/6a5558fb/video/tos/alisg/tos-alisg-pve-0037c001/ogHqPgDOQBBEJ5hjfEAgI8TF6N55NmCwYfcRUu/?a=1233&bti=NEBzNTY6QGo6OjZALnAjNDQuYCMxNDNg&&bt=921&ft=gKfIn8s6oA-O12NvgPZZzIxRW-jyO3_45SY&mime_type=video_mp4&rc=ZWk1NGg1ZGhpZzc4PDNkNEBpajRuM2o5cmhnOzMzODczNEA2XzYzY18uNl4xL2BeLS8vYSM2YnNrMmRjbHJhLS1kMTFzcw%3D%3D&vvpl=1&l=202607131529544A102FF5115A2A0AEC78&btag=e00088000",
    "carousel_urls": [],
    "format": "TikTok",
    "caption": "somewhere between a dream and a 2016 travel edit \u2708\ufe0f\ud83c\udf0a #cinematic #filmmaking #dji #elnido #cinematography    @DJI Philippines @DJI Official",
    "timestamp": "2026-06-25T07:46:04+00:00",
    "likes": 70224,
    "comments": 658,
    "shares": 14874,
    "views": 357689,
    "saves": 14072,
    "music": "original sound - andreividanes",
    "audio_song": "original sound - andreividanes",
    "audio_artist": "Andrei Vidanes",
    "audio_id": "7655236172404116231",
    "audio_is_original": true,
    "engagement": 85756,
    "trendScore": 24.0,
    "velocity": 19522,
    "ageDays": 18.3,
    "source": "keyword:cinematic travel",
    "isNewAccount": true
  },
  {
    "platform": "tiktok",
    "account": "addis.josh",
    "url": "https://www.tiktok.com/@addis.josh/video/7657774506164981006",
    "thumbnail": "https://p19-common-sign.tiktokcdn-us.com/tos-useast5-p-0068-tx/oEFDtJeUiAjtHYnCE8heCjwCk2LfQTsuIbSAID~tplv-tiktokx-cropcenter:500:800.jpeg?biz_tag=musically_video.video_cover&dr=9638&idc=useast8&ps=13740610&refresh_token=d48d4cc8&shcp=9b759fb9&shp=c1333099&t=4d5b0474&x-expires=1783976400&x-signature=lGwB9iUYpcIcHFGG2enQigejhho%3D",
    "video": "https://v16m.tiktokcdn-us.com/7398aa4da3ff394f6095afe13f3962f2/6a555908/video/tos/useast5/tos-useast5-ve-0068c004-tx/oMfr4enkiCHF28JIQEWmeEA4sNDAXU3wDIjFEd/?a=1233&bti=NTY6QGo0QHM6OjZANDQuYCMucCMxNDNg&&bt=1297&ft=gKfIn8s6oA-O12Nv~wZZzIxRPh-z93_45SY&mime_type=video_mp4&rc=aDw4ZzM8NGg2Omg8PDM5O0BpamZzdng5cnN4PDMzZzczNEA1XjAxXzY1XzMxLzIzNF5gYSMxYTMzMmRzLi9hLS1kMS9zcw%3D%3D&vvpl=1&l=2026071315301886F48511E56A5F066C01&btag=e000b8000",
    "carousel_urls": [],
    "format": "TikTok",
    "caption": "Brian scooba smells like lil uzi  #Hiking #natureedits #lowcortisol #travelcontent #cinematography",
    "timestamp": "2026-07-02T03:56:30+00:00",
    "likes": 25958,
    "comments": 139,
    "shares": 941,
    "views": 112757,
    "saves": 2192,
    "music": "original sound - addis.josh",
    "audio_song": "original sound - addis.josh",
    "audio_artist": "Josh",
    "audio_id": "7657774575098383117",
    "audio_is_original": true,
    "engagement": 27038,
    "trendScore": 24.0,
    "velocity": 9820,
    "ageDays": 11.5,
    "source": "keyword:travel cinematography",
    "isNewAccount": true
  },
  {
    "platform": "tiktok",
    "account": "cityvibes.nyc",
    "url": "https://www.tiktok.com/@cityvibes.nyc/video/7661627827091000598",
    "thumbnail": "https://p19-common-sign.tiktokcdn-us.com/tos-no1a-p-0037-no/owBjAi1KviBAVCcAE1iB7XPzIAy4wS3QCSTfYI~tplv-tiktokx-cropcenter:500:800.jpeg?biz_tag=musically_video.video_cover&dr=9638&idc=useast5&ps=13740610&refresh_token=e7efe994&shcp=9b759fb9&shp=c1333099&t=4d5b0474&x-expires=1783976400&x-signature=DdRqwHH7eGhNPbA1wWWQxoZ95zA%3D",
    "video": "https://v16m.tiktokcdn-us.com/1775812b04fa72b5a99a6045d9fffcdb/6a55590e/video/tos/no1a/tos-no1a-ve-0068-no/okABOLwxIpdFGSAOjeCDxeI7AIIeLV3RjUiwgY/?a=1233&bti=NEBzNTY6QGo6OjZALnAjNDQuYCMxNDNg&&bt=2673&ft=gKfIn8s6oA-O12NvgPZZzIxRW-jyO3_45SY&mime_type=video_mp4&rc=NDdoOzY3ZTM1PDk0PDU7N0BpMztqbng5cjlyPDMzbzczNUBgLTE0MmI2XzQxYWBeMmNfYSNvbDJvMmQ0ZjZhLS1kMTFzcw%3D%3D&vvpl=1&l=202607131529544A102FF5115A2A0AEC78&btag=e00090000",
    "carousel_urls": [],
    "format": "TikTok",
    "caption": "Post 221 | \ud83d\uddfd New York City Transformed Into a Winter Wonderland | Cinematic 4K Travel Film \u2744\ufe0f From Manhattan to Times Square | The Most Magical Snowfall in New York City #unitedstates  #nycsnow  #foryouusa  #timesquare  #searchinsightview2025",
    "timestamp": "2026-07-12T13:09:05+00:00",
    "likes": 7106,
    "comments": 24,
    "shares": 2072,
    "views": 41168,
    "saves": 1203,
    "music": "original sound - hiphop.classics7",
    "audio_song": "original sound - hiphop.classics7",
    "audio_artist": "Hip-hop classics",
    "audio_id": "7494063689889958661",
    "audio_is_original": true,
    "engagement": 9202,
    "trendScore": 22.4,
    "velocity": 37501,
    "ageDays": 1.1,
    "source": "keyword:cinematic travel",
    "isNewAccount": true
  },
  {
    "platform": "tiktok",
    "account": "mountainbrynn",
    "url": "https://www.tiktok.com/@mountainbrynn/video/7658445776103804173",
    "thumbnail": "https://p16-common-sign.tiktokcdn-us.com/tos-useast5-p-0068-tx/o4mWIButCrUAhKeHLeQXCXkIjHeM0AakNB8pnQ~tplv-tiktokx-cropcenter:500:800.jpeg?biz_tag=musically_video.video_cover&dr=9638&idc=useast5&ps=13740610&refresh_token=43e69246&shcp=9b759fb9&shp=c1333099&t=4d5b0474&x-expires=1783976400&x-signature=q0jVoWvrg5vWhhesI14T7ePe5ho%3D",
    "video": "https://v16m.tiktokcdn-us.com/770958eef1361fdfe24803fa9fe0662f/6a5558e9/video/tos/useast5/tos-useast5-pve-0068-tx/owyNQSEDt9fDZ6tgiqEQE0IICMFCCRASzWBbeg/?a=1233&bti=NEBzNTY6QGo6OjZALnAjNDQuYCMxNDNg&&bt=2657&ft=gKfIn8buoTfR12NvHPZZzIxRl7PhZQ_45SY&mime_type=video_mp4&rc=ZzlnPGllNzg3OzY3Njo6NkBpM3Q5O3c5cm83PDMzZzczNEBfLjVhMF8uNjUxMjE2LzQ0YSMvbV9jMmRrMzFhLS1kMS9zcw%3D%3D&vvpl=1&l=202607131529572C479AB591AA160A8B01&btag=e000b8000",
    "carousel_urls": [],
    "format": "TikTok",
    "caption": "\ud83d\udccdStoos Ridge, Switzerland \ud83c\udfd4\ufe0fEasily the most beautiful view I\u2019ve seen #travel #switzerland #photography #views #fyp",
    "timestamp": "2026-07-03T23:21:28+00:00",
    "likes": 407439,
    "comments": 2626,
    "shares": 39354,
    "views": 2015700,
    "saves": 60165,
    "music": "original sound - pr.khriz",
    "audio_song": "original sound - pr.khriz",
    "audio_artist": "pr.khriz\u271d\ufe0e\ud83c\uddf5\ud83c\uddf7",
    "audio_id": "7585297102423542558",
    "audio_is_original": true,
    "engagement": 449419,
    "trendScore": 22.3,
    "velocity": 208394,
    "ageDays": 9.7,
    "source": "keyword:travel film",
    "isNewAccount": true
  },
  {
    "platform": "tiktok",
    "account": "lifeideo",
    "url": "https://www.tiktok.com/@lifeideo/video/7654280162988543250",
    "thumbnail": "https://p16-common-sign.tiktokcdn-us.com/tos-alisg-p-0037/oUUBOyJA0XSDkfrMFwwR0yfcEGBF5dEqgIwIMt~tplv-tiktokx-cropcenter:500:800.jpeg?biz_tag=musically_video.video_cover&dr=9638&idc=useast5&ps=13740610&refresh_token=c6e35008&shcp=9b759fb9&shp=c1333099&t=4d5b0474&x-expires=1783976400&x-signature=QX5zpl%2FXeUdhWbjLQU3NWLU2Q2E%3D",
    "video": "https://v19.tiktokcdn-us.com/e3d3ab20a0eabb4f528d2744a25ca548/6a5558de/video/tos/alisg/tos-alisg-pve-0037c001/ocfRIEcfwryYACJ5GaB6EtSdgQF0BqAXOMDUWE/?a=1233&bti=NEBzNTY6QGo6OjZALnAjNDQuYCMxNDNg&&bt=1548&ft=gKfIn8s6oA-O12NvgPZZzIxRW-jyO3_45SY&mime_type=video_mp4&rc=ODY4Z2U1OzplNmkzZGUzaEBpMzk7bG85cmZxOzMzODczNEBfM18tY14yXmIxNjViMjItYSNsbF5zMmRrYnBhLS1kMTFzcw%3D%3D&vvpl=1&l=202607131529544A102FF5115A2A0AEC78&btag=e000b0000",
    "carousel_urls": [],
    "format": "TikTok",
    "caption": "8PM in Seoul \ud83c\udf19 \ud83d\udccdTtukseom Hangang Park, Seoul \ud83d\udccd\ub69d\uc12c\ud55c\uac15\uacf5\uc6d0 #Seoul #SeoulKorea #VisitSeoul #CinematicVideo #TravelReels",
    "timestamp": "2026-06-22T17:56:24+00:00",
    "likes": 27764,
    "comments": 107,
    "shares": 6633,
    "views": 161370,
    "saves": 3855,
    "music": "I Thought I Saw Your Face Today",
    "audio_song": "I Thought I Saw Your Face Today",
    "audio_artist": "She & Him",
    "audio_id": "6767541102724532225",
    "audio_is_original": false,
    "engagement": 34504,
    "trendScore": 21.4,
    "velocity": 7721,
    "ageDays": 20.9,
    "source": "keyword:cinematic travel",
    "isNewAccount": true
  },
  {
    "platform": "tiktok",
    "account": "ashvardanyann",
    "url": "https://www.tiktok.com/@ashvardanyann/video/7656340259789131022",
    "thumbnail": "https://p16-common-sign.tiktokcdn-us.com/tos-useast5-p-0068-tx/oM1EkyZQIvfIkFgCUANDfHHjBeAFNiZAYZWUIh~tplv-tiktokx-cropcenter:500:800.jpeg?biz_tag=musically_video.video_cover&dr=9638&idc=useast5&ps=13740610&refresh_token=c12174a4&shcp=9b759fb9&shp=c1333099&t=4d5b0474&x-expires=1783976400&x-signature=hq%2FQAHevmxiSpTyl7tiHdLJBxIM%3D",
    "video": "https://v16m.tiktokcdn-us.com/5789c5d442e69cd55383f1e07e6b1e1f/6a5558dc/video/tos/useast5/tos-useast5-pve-0068-tx/oQCEAEfQjBkIUAyfAUHgtZRnhUpDICFekvMHqZ/?a=1233&bti=NEBzNTY6QGo6OjZALnAjNDQuYCMxNDNg&&bt=1878&ft=gKfIn8s6oA-O12NvgPZZzIxRW-jyO3_45SY&mime_type=video_mp4&rc=ZmVkMzdkPGVnNWY1OGQ5NUBpam5rcnk5cmlmPDMzZzczNEBiMTYtNjRjXi0xYzA1Yl5hYSMwZmBrMmRrZC1hLS1kMS9zcw%3D%3D&vvpl=1&l=202607131529544A102FF5115A2A0AEC78&btag=e000b0000",
    "carousel_urls": [],
    "format": "TikTok",
    "caption": "be yourself mate! trust #chalant #travel #cinematic #nature #yosemitenationalpark",
    "timestamp": "2026-06-28T07:10:56+00:00",
    "likes": 113276,
    "comments": 73,
    "shares": 4304,
    "views": 553643,
    "saves": 6760,
    "music": "original sound - trace.young",
    "audio_song": "original sound - trace.young",
    "audio_artist": "Trace Young \u2020",
    "audio_id": "7627238272384633631",
    "audio_is_original": true,
    "engagement": 117653,
    "trendScore": 21.3,
    "velocity": 36076,
    "ageDays": 15.3,
    "source": "keyword:cinematic travel",
    "isNewAccount": true
  },
  {
    "platform": "tiktok",
    "account": "veli.keo",
    "url": "https://www.tiktok.com/@veli.keo/video/7659441097331985678",
    "thumbnail": "https://p19-common-sign.tiktokcdn-us.com/tos-useast5-p-0068-tx/oA2pn8AMQQoCgeAH5MUEvMeElgbgkqA8AAfXEr~tplv-tiktokx-cropcenter:500:800.jpeg?biz_tag=musically_video.video_cover&dr=9638&idc=useast8&ps=13740610&refresh_token=7924d8ba&shcp=9b759fb9&shp=c1333099&t=4d5b0474&x-expires=1783976400&x-signature=Y7KAyHZrBAkLGql%2Fvo1xTE0LTwI%3D",
    "video": "https://v16m.tiktokcdn-us.com/b2e9d2dbadf64a4a5af2c4f7e4da3669/6a555914/video/tos/useast5/tos-useast5-ve-0068c001-tx/o8ILEQD5VztSAiBqniJGf0IbaZ8CjiBgSHeXBZ/?a=1233&bti=NEBzNTY6QGo6OjZALnAjNDQuYCMxNDNg&&bt=301&ft=gKfIn8QLodzR12NvkwZZzIxRMQz_XF_45SY&mime_type=video_mp4&rc=aWRlaTM8NmY0aWQ8ZDVmNEBpM25ucHY5cmt2PDMzZzgzNEA0YC8wMi5fNjUxXjNhMl8zYSNhY3FnMmRzbTJhLS1kLy9zcw%3D%3D&vvpl=1&l=20260713153008E95C0398557BBB07FC19&btag=e00088000",
    "carousel_urls": [],
    "format": "TikTok",
    "caption": "i woke up at 5am #cinematography #colorgrading #editing #fyp #wakeupearly  shot on a Sony A7IV",
    "timestamp": "2026-07-06T15:43:34+00:00",
    "likes": 448083,
    "comments": 2029,
    "shares": 11105,
    "views": 2256389,
    "saves": 55228,
    "music": "original sound - veli.keo",
    "audio_song": "original sound - veli.keo",
    "audio_artist": "velikeo",
    "audio_id": "7659441141795932941",
    "audio_is_original": true,
    "engagement": 461217,
    "trendScore": 20.4,
    "velocity": 322779,
    "ageDays": 7.0,
    "source": "keyword:cinematic photography",
    "isNewAccount": true
  },
  {
    "platform": "tiktok",
    "account": "isaiahjwalter",
    "url": "https://www.tiktok.com/@isaiahjwalter/video/7655414747151584525",
    "thumbnail": "https://p19-common-sign.tiktokcdn-us.com/tos-useast5-p-0068-tx/oAzlFfCTDDBqFzZEM6EfXwQzPBSQnuOggURb8A~tplv-tiktokx-cropcenter:500:800.jpeg?biz_tag=musically_video.video_cover&dr=9638&idc=useast5&ps=13740610&refresh_token=a92cf16b&shcp=9b759fb9&shp=c1333099&t=4d5b0474&x-expires=1783976400&x-signature=xk%2BDYKn4ec%2F94zSyYm6tuBB3LqY%3D",
    "video": "https://v45.tiktokcdn-us.com/651b355979f06604aa78f595502d3223/6a5558ee/video/tos/useast5/tos-useast5-pve-0068-tx/oMSmOyeGIgBTGcoROfWcDeFv1FnAfI4YL3gZQA/?a=1233&bti=NEBzNTY6QGo6OjZALnAjNDQuYCMxNDNg&&bt=665&ft=aEKfuqT0mI2PD125QqqI3wUThrlcMeF~O5&mime_type=video_mp4&rc=OWk1aTU3PDY6OjQ2aDs4OUBpajRsdGo5cjZxOzMzZzczNEBiXmFfYjJhXy8xMF9hMS0uYSNfYmE2MmQ0cnJhLS1kMS9zcw%3D%3D&vvpl=1&l=20260713153011635B46952589FA099C73&btag=e000b5000",
    "carousel_urls": [],
    "format": "TikTok",
    "caption": "So much more to life than materialism #fyp #travel #filmmaking #cinematic",
    "timestamp": "2026-06-25T19:19:15+00:00",
    "likes": 5623,
    "comments": 34,
    "shares": 295,
    "views": 30331,
    "saves": 548,
    "music": "original sound - isaiahjwalter",
    "audio_song": "original sound - isaiahjwalter",
    "audio_artist": "Isaiah Walter",
    "audio_id": "7655414719264492302",
    "audio_is_original": true,
    "engagement": 5952,
    "trendScore": 19.6,
    "velocity": 1700,
    "ageDays": 17.8,
    "source": "keyword:travel filmmaker",
    "isNewAccount": true
  },
  {
    "platform": "tiktok",
    "account": "dulongducanh",
    "url": "https://www.tiktok.com/@dulongducanh/video/7658859260150893845",
    "thumbnail": "https://p19-common-sign.tiktokcdn-us.com/tos-alisg-p-0037/o0efRAQGpJdSC6lLIAAuJAI7RGOTeJjAhGQfCx~tplv-tiktokx-cropcenter:500:800.jpeg?biz_tag=musically_video.video_cover&dr=9638&idc=useast5&ps=13740610&refresh_token=6641e06b&shcp=9b759fb9&shp=c1333099&t=4d5b0474&x-expires=1783976400&x-signature=eyXYyTpV9ulNKiXJCj%2BfHN4ioko%3D",
    "video": "https://v16m.tiktokcdn-us.com/cba0a9cdcc6aa9edce2c6b56aa16fe42/6a555901/video/tos/alisg/tos-alisg-pve-0037c001/oYivFIwiEAko7EaBIViY1Zvj02EBQmAJQoEuA/?a=1233&bti=NEBzNTY6QGo6OjZALnAjNDQuYCMxNDNg&&bt=1342&ft=aEKfuqT0mI2PD125QqqI3wUThrlcMeF~O5&mime_type=video_mp4&rc=aDo8ZWg8ZjYzaDgzZ2c0ZkBpMzY1ZW45cm91PDMzODczNEBjYS9eNTY0X2MxYmMxLjJjYSNlZWlsMmRrazFhLS1kMTFzcw%3D%3D&vvpl=1&l=20260713153011635B46952589FA099C73&btag=e00088000",
    "carousel_urls": [],
    "format": "TikTok",
    "caption": "M\u1eddi b\u00e0 con v\u1ec1 mi\u1ec1n T\u00e2y \u0103n \u0111\u00e1m gi\u1ed7 \ud83e\udd79\u2728 #DuLongDuCanh #filmmaker #cinematic #travel #vietnam",
    "timestamp": "2026-07-05T02:05:46+00:00",
    "likes": 15571,
    "comments": 164,
    "shares": 2631,
    "views": 97713,
    "saves": 563,
    "music": "original sound - dulongducanh",
    "audio_song": "original sound - dulongducanh",
    "audio_artist": "\u0110\u1ee7 L\u00f4ng \u0110\u1ee7 C\u00e1nh",
    "audio_id": "7658859324488272647",
    "audio_is_original": true,
    "engagement": 18366,
    "trendScore": 18.8,
    "velocity": 11417,
    "ageDays": 8.6,
    "source": "keyword:travel filmmaker",
    "isNewAccount": true
  },
  {
    "platform": "tiktok",
    "account": "juliakursten",
    "url": "https://www.tiktok.com/@juliakursten/video/7661263937891061014",
    "thumbnail": "https://p19-common-sign.tiktokcdn-us.com/tos-no1a-p-0037-no/ocdRDEgvQdqJ3WEwQBSeQkFSLUyZRFfk3wAFbv~tplv-tiktokx-cropcenter:500:800.jpeg?biz_tag=musically_video.video_cover&dr=9638&idc=useast5&ps=13740610&refresh_token=e3f59f5c&shcp=9b759fb9&shp=c1333099&t=4d5b0474&x-expires=1783976400&x-signature=uwI5%2BB16bzcNSDo75AK1r0OiA04%3D",
    "video": "https://v45.tiktokcdn-us.com/3878d72ad23628b1deb8250108ae51cf/6a5558f4/video/tos/no1a/tos-no1a-ve-0068-no/oQNICGRZiiAujKQwEIWBy337SoRBN71SQClfAw/?a=1233&bti=NEBzNTY6QGo6OjZALnAjNDQuYCMxNDNg&&bt=547&ft=aEKfuqT0mI2PD125QqqI3wUThrlcMeF~O5&mime_type=video_mp4&rc=NTs7M2hlaDw5ZDw4NGloN0Bpajt5PHU5cnU3PDMzbzczNUBeXl9jLjAtNTExYy9gLi01YSNga2JrMmRzYTZhLS1kMTFzcw%3D%3D&vvpl=1&l=20260713153011635B46952589FA099C73&btag=e000bd000",
    "carousel_urls": [],
    "format": "TikTok",
    "caption": "Sailing Greenland \ud83c\uddec\ud83c\uddf1\u26f5\ufe0f\u26f5\ufe0f",
    "timestamp": "2026-07-11T13:37:02+00:00",
    "likes": 14691,
    "comments": 72,
    "shares": 1217,
    "views": 90524,
    "saves": 1281,
    "music": "original sound - juliakursten",
    "audio_song": "original sound - juliakursten",
    "audio_artist": "Julia | FILMMAKER & TRAVEL",
    "audio_id": "7661263931898039062",
    "audio_is_original": true,
    "engagement": 15980,
    "trendScore": 17.7,
    "velocity": 43555,
    "ageDays": 2.1,
    "source": "keyword:travel filmmaker",
    "isNewAccount": true
  },
  {
    "platform": "tiktok",
    "account": "sonyalpha",
    "url": "https://www.tiktok.com/@sonyalpha/video/7659795686220647693",
    "thumbnail": "https://p16-common-sign.tiktokcdn-us.com/tos-useast5-p-0068-tx/oA76IgFzyUkFPqYNHCDAQemyjsUADCJIehE5fH~tplv-tiktokx-cropcenter:500:800.jpeg?biz_tag=musically_video.video_cover&dr=9638&idc=useast8&ps=13740610&refresh_token=a4d0b4de&shcp=9b759fb9&shp=c1333099&t=4d5b0474&x-expires=1783976400&x-signature=GkGa8ZBZot2f1oIy7dA5xRwvVZ8%3D",
    "video": "https://v16m.tiktokcdn-us.com/f2d8a0f0fabc038ac25e2fd632ab9a89/6a5558f7/video/tos/useast5/tos-useast5-pve-0068-tx/ok5cuNfiQCIVTB8qAWQERDKiMfNxVNESDBQBg9/?a=1233&bti=NEBzNTY6QGo6OjZALnAjNDQuYCMxNDNg&&bt=1150&ft=gKfIn8s6oA-O12Nv~wZZzIxRPh-z93_45SY&mime_type=video_mp4&rc=OTQ8ZzM8O2c7OmQ4NDZpZEBpM29tNXM5cjRqPDMzZzczNEBjYzRiYWBiXzIxNmBhLS5iYSM1bmdfMmRjczNhLS1kMS9zcw%3D%3D&vvpl=1&l=2026071315301886F48511E56A5F066C01&btag=e000b0000",
    "carousel_urls": [],
    "format": "TikTok",
    "caption": "Go outside, friend. Bring your Sony camera. Inspiration by @tootripsy with his Sony Alpha 7C II + 24-70mm F2.8 G Master II (an amazing, compact travel set up). #SonyAlpha #cinematicvideo",
    "timestamp": "2026-07-07T14:39:56+00:00",
    "likes": 3755,
    "comments": 15,
    "shares": 239,
    "views": 24477,
    "saves": 663,
    "music": "original sound - sonyalpha",
    "audio_song": "original sound - sonyalpha",
    "audio_artist": "Sony Alpha",
    "audio_id": "7659795806131587853",
    "audio_is_original": true,
    "engagement": 4009,
    "trendScore": 16.4,
    "velocity": 4056,
    "ageDays": 6.0,
    "source": "keyword:travel cinematography",
    "isNewAccount": true
  },
  {
    "platform": "tiktok",
    "account": "salman.wesal78",
    "url": "https://www.tiktok.com/@salman.wesal78/video/7658342258969726230",
    "thumbnail": "https://p16-common-sign.tiktokcdn-us.com/tos-no1a-p-0037-no/oU1LUbD1F5kGj5HjsjjIADeIo6mEIIAfAUeb0E~tplv-tiktokx-cropcenter:500:800.jpeg?biz_tag=musically_video.video_cover&dr=9638&idc=useast5&ps=13740610&refresh_token=0d66e020&shcp=9b759fb9&shp=c1333099&t=4d5b0474&x-expires=1783976400&x-signature=Gn7epgoHcB%2BkTMu5wDF1hHvlxUs%3D",
    "video": "https://v16m.tiktokcdn-us.com/a016d01909f6426c93af1232ab128c28/6a55594b/video/tos/no1a/tos-no1a-ve-0068-no/oghAFfhuLMmjbI0ffBXoAoiQjAqUB5N8IUDUy8/?a=1233&bti=NTY6QGo0QHM6OjZANDQuYCMucCMxNDNg&&bt=739&ft=gKfIn8buoTfR12NvHPZZzIxRl7PhZQ_45SY&mime_type=video_mp4&rc=N2Y8ODc4OzZmN2czaTc7aUBpMzdnNnc5cjR4PDMzbzczNUAwLjFiYmIzXl8xMDAwNTEuYSMxcWJeMmRrXjBhLS1kMTFzcw%3D%3D&vvpl=1&l=202607131529572C479AB591AA160A8B01&btag=e00090000",
    "carousel_urls": [],
    "format": "TikTok",
    "caption": "I've received this question many times, so I wanted to answer it honestly and respectfully. When creating content, I try to balance showing everyday life with respecting people's privacy, local customs, and the realities of filming in Afghanistan. Thank you for asking thoughtful questions. They help me create better content. @berceoelfuego @\ud83e\udde1 Anelej \ud83d\udc9a @izzy @Leonie #kabul #afghanculture #afghanistan #travelafghanistan\ud83c\udde6\ud83c\uddeb",
    "timestamp": "2026-07-03T16:39:26+00:00",
    "likes": 231101,
    "comments": 1432,
    "shares": 10299,
    "views": 1495580,
    "saves": 15631,
    "music": "original sound - salman.wesal78",
    "audio_song": "original sound - salman.wesal78",
    "audio_artist": "Salman wesal",
    "audio_id": "7658342300023606038",
    "audio_is_original": true,
    "engagement": 242832,
    "trendScore": 16.2,
    "velocity": 150283,
    "ageDays": 10.0,
    "source": "keyword:travel film",
    "isNewAccount": true
  },
  {
    "platform": "tiktok",
    "account": "icerolling880",
    "url": "https://www.tiktok.com/@icerolling880/video/7658952557229772053",
    "thumbnail": "https://p16-common-sign.tiktokcdn-us.com/tos-alisg-p-0037/owtEmEfMI6uEUDSB9KxDfB1R8lAFCLgglhTqIL~tplv-tiktokx-origin.image?biz_tag=musically_video.video_cover&dr=8593&idc=useast5&ps=933b5bde&refresh_token=c16e4218&s=SEARCH&sc=cover&shcp=c1333099&shp=d05b14bd&t=bacd0480&x-expires=1784041200&x-signature=A5YOCUdZkGHLy1gcQQNiy92qIIY%3D",
    "video": "https://v16m.tiktokcdn-us.com/68cf4f5550984cc66c80aa2a4c6a96a1/6a5558fc/video/tos/alisg/tos-alisg-pve-0037c001/oUEmclIgUkAF1EgElMR9uSfLj8DuBBBEfQNq6K/?a=1233&bti=NEBzNTY6QGo6OjZALnAjNDQuYCMxNDNg&&bt=586&ft=BIcq8V~3wUxl7K2gUtIvk84jWLpi0L~~QjKJfa5hgG0P3-I&mime_type=video_mp4&rc=OGc0aWY0ODo8ZGg2OzM4N0Bpandna3E5cjwzPDMzODczNEBjMTQxYzQxNi4xXjNjNGFhYSNuc2JiMmRjcjJhLS1kMTFzcw%3D%3D&vvpl=1&l=20260713153015F8627713AE64650B505C&btag=e000b8000",
    "carousel_urls": [],
    "format": "TikTok",
    "caption": "BLVCKROLLING BANGSAEN TOSHIN \ud83e\udd77\ud83d\udc3a\ud83e\udebd #blvckrolling #hoodies #rollingshot #cinematic #fyp",
    "timestamp": "2026-07-05T08:07:39+00:00",
    "likes": 2409,
    "comments": 96,
    "shares": 738,
    "views": 20633,
    "saves": 115,
    "music": "original sound - icerolling880",
    "audio_song": "original sound - icerolling880",
    "audio_artist": "I C E BLVCKROLLING",
    "audio_id": "7658952580410493717",
    "audio_is_original": true,
    "engagement": 3243,
    "trendScore": 15.7,
    "velocity": 2483,
    "ageDays": 8.3,
    "source": "keyword:cinematic b roll",
    "isNewAccount": true
  },
  {
    "platform": "tiktok",
    "account": "peind.play",
    "url": "https://www.tiktok.com/@peind.play/video/7656485449510194440",
    "thumbnail": "https://p16-common-sign.tiktokcdn-us.com/tos-alisg-p-0037/o8EBIAgAKTCIA9B1RiBbfAaLgZyB3iAwUdKOBd~tplv-tiktokx-cropcenter:500:800.jpeg?biz_tag=musically_video.video_cover&dr=9638&idc=useast5&ps=13740610&refresh_token=6a5d05d0&shcp=9b759fb9&shp=c1333099&t=4d5b0474&x-expires=1783976400&x-signature=1sM4wC9gpa%2F1RQ47BONQB%2BEAIvY%3D",
    "video": "https://v16m.tiktokcdn-us.com/e6c81a2ed901fffe834f9af9a7c7d06f/6a555973/video/tos/alisg/tos-alisg-pve-0037/okFKTRKqQA2fB7uQEmwU9VTBpdBfEWrYCKQgID/?a=1233&bti=NTY6QGo0QHM6OjZANDQuYCMucCMxNDNg&&bt=902&ft=gKfIn8buoTfR12NvHPZZzIxRl7PhZQ_45SY&mime_type=video_mp4&rc=Zjs7aTM8aGYzPDY2NDhoOUBpM3VxcG05cmVuPDMzODgzNUBfY2BiNi8xNS8xYDVjMDYuYSM1cy8vMmRrMi1hLS1kLzZzcw%3D%3D&vvpl=1&l=202607131529572C479AB591AA160A8B01&btag=e00088000",
    "carousel_urls": [],
    "format": "TikTok",
    "caption": "Qua \u1ed0ng K\u00ednh Kaia - Shortfilm | Phuocdienle.  M\u1ed9t nhi\u1ebfp \u1ea3nh gia tr\u1edf v\u1ec1 qu\u00ea h\u01b0\u01a1ng sau nhi\u1ec1u n\u0103m... \ud83d\udcf8\ud83c\udf34  #heplaytogether #playtogethervng #playtogether #ptgcreator #shortfilm",
    "timestamp": "2026-06-28T16:34:01+00:00",
    "likes": 26325,
    "comments": 511,
    "shares": 2154,
    "views": 192605,
    "saves": 1923,
    "music": "original sound - peind.play",
    "audio_song": "original sound - peind.play",
    "audio_artist": "\u0110\u1ea1o Di\u1ec5n Ch\u1ee5c View \ud83c\udfac",
    "audio_id": "7656485563721779986",
    "audio_is_original": true,
    "engagement": 28990,
    "trendScore": 15.1,
    "velocity": 12878,
    "ageDays": 15.0,
    "source": "keyword:travel film",
    "isNewAccount": true
  },
  {
    "platform": "tiktok",
    "account": "isabellevictoriafilms",
    "url": "https://www.tiktok.com/@isabellevictoriafilms/video/7659179343012252958",
    "thumbnail": "https://p19-common-sign.tiktokcdn-us.com/tos-useast8-p-0068-tx2/oYiExjVvEB3SNVkKZFiBAeIiRAwXA7KfEACqAt~tplv-tiktokx-cropcenter:500:800.jpeg?biz_tag=musically_video.video_cover&dr=9638&idc=useast5&ps=13740610&refresh_token=0b019ad0&shcp=9b759fb9&shp=c1333099&t=4d5b0474&x-expires=1783976400&x-signature=aPm3sQUmRuhfDgVyDUQpkXqk5DI%3D",
    "video": "https://v16m.tiktokcdn-us.com/094eec944f06f4c53b2979efb5ecfe09/6a5558e4/video/tos/useast8/tos-useast8-pve-0068-tx2/o0yEESHV7EAtxBX5p038KfQRWAE19BDJqIfRiF/?a=1233&bti=NTY6QGo0QHM6OjZANDQuYCMucCMxNDNg&&bt=859&ft=gKfIn8buoTfR12NvHPZZzIxRl7PhZQ_45SY&mime_type=video_mp4&rc=OWU0Z2g6NDhoNzw8aGU5OUBpM2t4aXQ5cjRnPDMzaTczNEA0NjEzLWI2Xy4xNDI1MzQ1YSNfZzRzMmRzcjJhLS1kMTJzcw%3D%3D&vvpl=1&l=202607131529572C479AB591AA160A8B01&btag=e000b8000",
    "carousel_urls": [],
    "format": "TikTok",
    "caption": "Adventure buddies for life >>> #traveltips #adventure #travel #filmmaking",
    "timestamp": "2026-07-05T22:47:51+00:00",
    "likes": 24098,
    "comments": 77,
    "shares": 2981,
    "views": 188318,
    "saves": 2016,
    "music": "original sound - isabellevictoriafilms",
    "audio_song": "original sound - isabellevictoriafilms",
    "audio_artist": "isabelle",
    "audio_id": "7659179344647965471",
    "audio_is_original": true,
    "engagement": 27156,
    "trendScore": 14.4,
    "velocity": 24470,
    "ageDays": 7.7,
    "source": "keyword:travel film",
    "isNewAccount": true
  },
  {
    "platform": "tiktok",
    "account": "dulongducanh",
    "url": "https://www.tiktok.com/@dulongducanh/video/7659639849850293524",
    "thumbnail": "https://p16-common-sign.tiktokcdn-us.com/tos-alisg-p-0037/oAERJ0QZmClMAsDACgfuFqAUAHIAeAPjBITqAE~tplv-tiktokx-cropcenter:500:800.jpeg?biz_tag=musically_video.video_cover&dr=9638&idc=useast5&ps=13740610&refresh_token=132e4471&shcp=9b759fb9&shp=c1333099&t=4d5b0474&x-expires=1783976400&x-signature=kfe4OzS82y8pP71%2Fiz9gx%2BT%2BkEc%3D",
    "video": "https://v45.tiktokcdn-us.com/d53e7908b2e4060261b8a57b087ea73d/6a5559f2/video/tos/alisg/tos-alisg-pve-0037c001/oMeNQQoMUCgc1DUXQqTQVAIeIDeM8mJA8jEip7/?a=1233&bti=NEBzNTY6QGo6OjZALnAjNDQuYCMxNDNg&&bt=1282&ft=aEKfuqT0mI2PD125QqqI3wUThrlcMeF~O5&mime_type=video_mp4&rc=ODw2PDpoaDllNjs7aWY3OkBpM3R2dXU5cmk7PDMzODczNEBjYmMuMjFgX2ExLzYvXzZgYSNzaG1nMmRjMDNhLS1kMTFzcw%3D%3D&vvpl=1&l=20260713153011635B46952589FA099C73&btag=e0009d000",
    "carousel_urls": [],
    "format": "TikTok",
    "caption": "\u201cNg\u00e0y ti\u00ean th\u01b0\u1eddng\u201d  ng\u00e0y c\u1ee7a nh\u1eefng chu\u1ea9n b\u1ecb vun v\u00e9n, c\u1ee7a m\u00f9i kh\u00f3i b\u1ebfp \u0111\u1ed3ng qu\u00ea v\u00e0 ti\u1ebfng c\u01b0\u1eddi th\u1eaft ch\u1eb7t t\u00ecnh l\u00e0ng ngh\u0129a x\u00f3m. \u0110\u00e1m gi\u1ed7 mi\u1ec1n T\u00e2y kh\u00f4ng ch\u1ec9 l\u00e0 \u0111\u1ec3 nh\u1edb ng\u01b0\u1eddi \u0111i tr\u01b0\u1edbc, m\u00e0 c\u00f2n l\u00e0 c\u00e1i c\u1edb \u0111\u1ec3 ng\u01b0\u1eddi \u1edf l\u1ea1i x\u00edch l\u1ea1i g\u1ea7n nhau h\u01a1n \ud83d\udc96\u2728 #DuLongDuCanh #filmmaker #cinematic #travel #vietnam",
    "timestamp": "2026-07-07T04:34:45+00:00",
    "likes": 5775,
    "comments": 81,
    "shares": 500,
    "views": 54138,
    "saves": 259,
    "music": "original sound - dulongducanh",
    "audio_song": "original sound - dulongducanh",
    "audio_artist": "\u0110\u1ee7 L\u00f4ng \u0110\u1ee7 C\u00e1nh",
    "audio_id": "7659639920215280392",
    "audio_is_original": true,
    "engagement": 6356,
    "trendScore": 11.7,
    "velocity": 8387,
    "ageDays": 6.5,
    "source": "keyword:travel filmmaker",
    "isNewAccount": true
  },
  {
    "platform": "tiktok",
    "account": "julescinefilms",
    "url": "https://www.tiktok.com/@julescinefilms/video/7654534908165115169",
    "thumbnail": "https://p16-common-sign.tiktokcdn-us.com/tos-useast2a-p-0037-euttp/oo2iAZIazgBGdX0gBEjMAqovvdrjpDDBo6aEi~tplv-tiktokx-cropcenter:500:800.jpeg?biz_tag=musically_video.video_cover&dr=9638&idc=useast5&ps=13740610&refresh_token=b7c7da52&shcp=9b759fb9&shp=c1333099&t=4d5b0474&x-expires=1783976400&x-signature=gHm0ypofaDDnX%2Fxs4OqwTmLjzX8%3D",
    "video": "https://v45.tiktokcdn-us.com/c8086224b110c74cbfe669d8cf5de749/6a5558f4/video/tos/useast2a/tos-useast2a-ve-0068c001-euttp/o8rjGvCEIqiDgz6BdudXwOiZBAQ0apXAMEaWo/?a=1233&bti=NEBzNTY6QGo6OjZALnAjNDQuYCMxNDNg&&bt=1373&ft=aEKfuqT0mI2PD125QqqI3wUThrlcMeF~O5&mime_type=video_mp4&rc=NjQ0Zmg5ZDlmPDRnOzU2ZkBpM3RudG05cjM4OzMzZjczNUAzM18zMC1hNWExMDBiNi1fYSNoYGcuMmRrbnFhLS1kMTNzcw%3D%3D&vvpl=1&l=20260713153011635B46952589FA099C73&btag=e000bd000",
    "carousel_urls": [],
    "format": "TikTok",
    "caption": "this is the life.\ud83c\udf1e #cinematic #filmmaking",
    "timestamp": "2026-06-23T10:24:58+00:00",
    "likes": 10812,
    "comments": 32,
    "shares": 465,
    "views": 100131,
    "saves": 960,
    "music": "This Is The Life",
    "audio_song": "This Is The Life",
    "audio_artist": "Amy Macdonald",
    "audio_id": "6937182500980541442",
    "audio_is_original": false,
    "engagement": 11309,
    "trendScore": 11.3,
    "velocity": 4954,
    "ageDays": 20.2,
    "source": "keyword:travel filmmaker",
    "isNewAccount": true
  },
  {
    "platform": "tiktok",
    "account": "justcreate_1",
    "url": "https://www.tiktok.com/@justcreate_1/video/7656789635279981841",
    "thumbnail": "https://p19-common-sign.tiktokcdn-us.com/tos-alisg-p-0037/ooFGdRDqQAzeBhQDEqqm5RYBcPCfIOmQES3gID~tplv-tiktokx-cropcenter:500:800.jpeg?biz_tag=musically_video.video_cover&dr=9638&idc=useast5&ps=13740610&refresh_token=73eb1083&shcp=9b759fb9&shp=c1333099&t=4d5b0474&x-expires=1783976400&x-signature=1bKfJvxaOvpOL6MQtFsZCSv8w6g%3D",
    "video": "https://v16m.tiktokcdn-us.com/e0346b84e4aa2378e038e1db3e424b70/6a5558e5/video/tos/alisg/tos-alisg-pve-0037c001/oc6mrDQKIAcQSDgEqBwET9GDfQaRg7FmqEBquf/?a=1233&bti=NEBzNTY6QGo6OjZALnAjNDQuYCMxNDNg&&bt=832&ft=gKfIn8s6oA-O12NvgPZZzIxRW-jyO3_45SY&mime_type=video_mp4&rc=ZjhlNTo2OmU5OTo4ZTM8Z0BpajRnb285cjc5PDMzODczNEBhMzUvLjEzNi8xMDFgXzUxYSNvcV4xMmQ0MC5hLS1kMWBzcw%3D%3D&vvpl=1&l=202607131529544A102FF5115A2A0AEC78&btag=e000b8000",
    "carousel_urls": [],
    "format": "TikTok",
    "caption": "[just template] If the Capcut icon doesn\u2019t show, just check my profile and find the video again. #CapCut #cinematic #Vlog #travel #moments",
    "timestamp": "2026-06-29T12:15:13+00:00",
    "likes": 8564,
    "comments": 23,
    "shares": 488,
    "views": 83035,
    "saves": 3147,
    "music": "original sound - justcreate_1",
    "audio_song": "original sound - justcreate_1",
    "audio_artist": "JC",
    "audio_id": "7656789871663303431",
    "audio_is_original": true,
    "engagement": 9075,
    "trendScore": 10.9,
    "velocity": 5874,
    "ageDays": 14.1,
    "source": "keyword:cinematic travel",
    "isNewAccount": true
  },
  {
    "platform": "tiktok",
    "account": "lifeoflukas43",
    "url": "https://www.tiktok.com/@lifeoflukas43/video/7658317004482301217",
    "thumbnail": "https://p19-common-sign.tiktokcdn-us.com/tos-useast2a-p-0037-euttp/o0RF6D0tAfuIdGsqZ8mFE6URIB2fmdQH3QDzEm~tplv-tiktokx-cropcenter:500:800.jpeg?biz_tag=musically_video.video_cover&dr=9638&idc=useast8&ps=13740610&refresh_token=3e16bb16&shcp=9b759fb9&shp=c1333099&t=4d5b0474&x-expires=1783976400&x-signature=mzrvq4Z6X6xySNL1X7xKYOJY%2BEo%3D",
    "video": "https://v16m.tiktokcdn-us.com/147cf6c22b5f34dd1e3c9cba03b3947b/6a5558f6/video/tos/useast2a/tos-useast2a-ve-0068c001-euttp/og8BCU0fRH9qFDAfI6sZRzdDQENEmwQ2mtRME3/?a=1233&bti=NEBzNTY6QGo6OjZALnAjNDQuYCMxNDNg&&bt=1079&ft=gKfIn8QLodzR12NvkwZZzIxRMQz_XF_45SY&mime_type=video_mp4&rc=ZDs5aTg8OWQ8ZmY6NGZlNUBpandvZ3k5cmd2PDMzZjczNUBiYDU2LzYwXzIxMy8vYDViYSNgNWlnMmQ0cTBhLS1kMTNzcw%3D%3D&vvpl=1&l=20260713153008E95C0398557BBB07FC19&btag=e000b8000",
    "carousel_urls": [],
    "format": "TikTok",
    "caption": "43FILM LUTs \u2013 out now \ud83c\udfac Cinematic looks for Sony S-Log3, DJI D-Log M & Insta360 I-Log \u2013 built and tested in real productions. First 48 hours only: 20% off with code LAUNCH20. Get yours \u2192 www.rredirected.de/luts #luts #43filmluts #davinciresolve #colorgrading #cinematic",
    "timestamp": "2026-07-03T15:01:20+00:00",
    "likes": 4576,
    "comments": 33,
    "shares": 180,
    "views": 44149,
    "saves": 938,
    "music": "original sound - lifeoflukas43",
    "audio_song": "original sound - lifeoflukas43",
    "audio_artist": "lifeoflukas",
    "audio_id": "7658317018269666080",
    "audio_is_original": true,
    "engagement": 4789,
    "trendScore": 10.8,
    "velocity": 4406,
    "ageDays": 10.0,
    "source": "keyword:cinematic photography",
    "isNewAccount": true
  },
  {
    "platform": "tiktok",
    "account": "r0nin.lee",
    "url": "https://www.tiktok.com/@r0nin.lee/video/7656647701517421838",
    "thumbnail": "https://p16-common-sign.tiktokcdn-us.com/tos-useast5-p-0068-tx/o0EACqeEtCuAWgRlrdIABFEDd5Dv1QABZf7Q1S~tplv-tiktokx-cropcenter:500:800.jpeg?biz_tag=musically_video.video_cover&dr=9638&idc=useast8&ps=13740610&refresh_token=d707b339&shcp=9b759fb9&shp=c1333099&t=4d5b0474&x-expires=1783976400&x-signature=AD03urZrVpH%2Bw%2F%2Brttpq7X3FAhE%3D",
    "video": "https://v16m.tiktokcdn-us.com/eabda353f11d4c5e1ec11fd8dcec1283/6a555919/video/tos/useast5/tos-useast5-pve-0068-tx/oML8xeEIQHAUIOgfrwFkDuSvwWAAOIAmDCejgw/?a=1233&bti=NTY6QGo0QHM6OjZANDQuYCMucCMxNDNg&&bt=859&ft=gKfIn8QLodzR12NvkwZZzIxRMQz_XF_45SY&mime_type=video_mp4&rc=Z2RoNjo5ZDQ4NjVoN2c1OEBpM3I0b3I5cjV4PDMzZzczNEBjLmMzNmEvNTMxY2AuLTQyYSNwY2A2MmQ0LS1hLS1kMS9zcw%3D%3D&vvpl=1&l=20260713153008E95C0398557BBB07FC19&btag=e00088000",
    "carousel_urls": [],
    "format": "TikTok",
    "caption": "DAY 59/60: The Life of a Student Videographer I post all my videos in 5:4 (1350\u00d71080), and it\u2019s become my favorite format. I love the cinematic look of horizontal videos, but vertical performs better because it fills more of the screen. 5:4 is the perfect middle ground\u2014it keeps the horizontal feel while taking up more space in the feed. It also lets me shoot everything horizontally without rotating my camera and simply crop in during editing. It\u2019s the best of both worlds. Follow me, to be part of my journey  #videography #students #cinematographers #series #videographytips",
    "timestamp": "2026-06-29T03:03:56+00:00",
    "likes": 6099,
    "comments": 155,
    "shares": 157,
    "views": 60740,
    "saves": 1600,
    "music": "original sound - r0nin.lee",
    "audio_song": "original sound - r0nin.lee",
    "audio_artist": "r0nin.lee",
    "audio_id": "7656647786904996621",
    "audio_is_original": true,
    "engagement": 6411,
    "trendScore": 10.6,
    "velocity": 4183,
    "ageDays": 14.5,
    "source": "keyword:cinematic photography",
    "isNewAccount": true
  },
  {
    "platform": "tiktok",
    "account": "oldbutgold998",
    "url": "https://www.tiktok.com/@oldbutgold998/video/7656853193904622870",
    "thumbnail": "https://p16-common-sign.tiktokcdn-us.com/tos-no1a-p-0037-no/oUFsugVqQAEPFxlBE3YpSRNBkUFfQeSAEJIgID~tplv-tiktokx-cropcenter:500:800.jpeg?biz_tag=musically_video.video_cover&dr=9638&idc=useast5&ps=13740610&refresh_token=37d0928b&shcp=9b759fb9&shp=c1333099&t=4d5b0474&x-expires=1783976400&x-signature=uYeH766klcNSds0GnWZjH6qEKu4%3D",
    "video": "https://v16m.tiktokcdn-us.com/c05bf904fe6a428f3a309c7d2bd7e747/6a55595c/video/tos/no1a/tos-no1a-ve-0068-no/o8CJGSIwysAikiUmVjI47Ifs12B8CAFEHQ51kC/?a=1233&bti=NTY6QGo0QHM6OjZANDQuYCMucCMxNDNg&&bt=354&ft=gKfIn8buoTfR12NvHPZZzIxRl7PhZQ_45SY&mime_type=video_mp4&rc=aDY4ZTM5OTxlOGQzZmU5aUBpM3I3ZXU5cjw8PDMzbzczNUBjXmJeLS4uXy0xYGEuMWE0YSNmYy5mMmRjai5hLS1kMTFzcw%3D%3D&vvpl=1&l=202607131529572C479AB591AA160A8B01&btag=e00090000",
    "carousel_urls": [],
    "format": "TikTok",
    "caption": "",
    "timestamp": "2026-06-29T16:21:05+00:00",
    "likes": 29506,
    "comments": 469,
    "shares": 4211,
    "views": 327567,
    "saves": 5991,
    "music": "original sound - thebaldeagle15",
    "audio_song": "original sound - thebaldeagle15",
    "audio_artist": "\ud83c\uddee\ud83c\uddea\ud83e\udd85The bald eagle\ud83e\udd85\ud83c\uddee\ud83c\uddea",
    "audio_id": "7542463316837534487",
    "audio_is_original": true,
    "engagement": 34186,
    "trendScore": 10.4,
    "velocity": 23457,
    "ageDays": 14.0,
    "source": "keyword:travel film",
    "isNewAccount": true
  },
  {
    "platform": "tiktok",
    "account": "jio46683",
    "url": "https://www.tiktok.com/@jio46683/video/7658365854555311368",
    "thumbnail": "https://p19-common-sign.tiktokcdn-us.com/tos-alisg-p-0037/oMD1PyfsAvlfUFAIW82EAuooEjQDeIsAjHCA5i~tplv-tiktokx-cropcenter:500:800.jpeg?biz_tag=musically_video.video_cover&dr=9638&idc=useast8&ps=13740610&refresh_token=a622e76a&shcp=9b759fb9&shp=c1333099&t=4d5b0474&x-expires=1783976400&x-signature=oUOm2jZewHn9h0zLLed5hvHD72I%3D",
    "video": "https://v16m.tiktokcdn-us.com/b3d31c908fe18acac72a069e814ac1db/6a5558f6/video/tos/alisg/tos-alisg-pve-0037c001/oUQiHKfGEQgfR90GQpfA7XMeXJ8gAFmC6IvP29/?a=1233&bti=NEBzNTY6QGo6OjZALnAjNDQuYCMxNDNg&&bt=544&ft=gKfIn8QLodzR12NvkwZZzIxRMQz_XF_45SY&mime_type=video_mp4&rc=PDQ7Ozo7NDk4ZzY4Njk0M0BpajV5Nnk5cnN5PDMzODczNEAzLjA2XmNfXmAxNDBjLmJgYSMvLzZoMmQ0aTBhLS1kMTFzcw%3D%3D&vvpl=1&l=20260713153008E95C0398557BBB07FC19&btag=e000b8000",
    "carousel_urls": [],
    "format": "TikTok",
    "caption": "cinematic photo edit on iphone cinematic photo edit on iphone tutorial cinematic photo edit on tiktok edit photo on iphone aesthetic how to take cinematic pictures iphone photography edits on iphone how to edit cinematic photo on iphone cinematic picture edit tutorial iphone cinematic videography how to edit photos to look cinematic #capcut #capcutpioneer",
    "timestamp": "2026-07-03T18:10:58+00:00",
    "likes": 7846,
    "comments": 209,
    "shares": 7908,
    "views": 168034,
    "saves": 1762,
    "music": "original sound - lyricsmonstar",
    "audio_song": "original sound - lyricsmonstar",
    "audio_artist": "LYRICS MON-STAR \u270d\ufe0e",
    "audio_id": "7560042576343731000",
    "audio_is_original": true,
    "engagement": 15963,
    "trendScore": 9.5,
    "velocity": 16993,
    "ageDays": 9.9,
    "source": "keyword:cinematic photography",
    "isNewAccount": true
  },
  {
    "platform": "tiktok",
    "account": "hito.bito",
    "url": "https://www.tiktok.com/@hito.bito/video/7655703986518887700",
    "thumbnail": "https://p16-common-sign.tiktokcdn-us.com/tos-alisg-p-0037/oEYQAIYJGuLQoAheeG8f5QkCLZYGRFL5QfOG9V~tplv-tiktokx-cropcenter:500:800.jpeg?biz_tag=musically_video.video_cover&dr=9638&idc=useast5&ps=13740610&refresh_token=73f688b9&shcp=9b759fb9&shp=c1333099&t=4d5b0474&x-expires=1783976400&x-signature=%2BPuLGXsanMLfbpkRDztkpa5HPiQ%3D",
    "video": "https://v19.tiktokcdn-us.com/543261fd8dfd252dae97efa631cd8d64/6a555901/video/tos/alisg/tos-alisg-pve-0037c001/o4We5zAf8AgUBuZwAMGoWlF4hQGQWRtqeQeRix/?a=1233&bti=NEBzNTY6QGo6OjZALnAjNDQuYCMxNDNg&&bt=2913&ft=gKfIn8buoTfR12NvHPZZzIxRl7PhZQ_45SY&mime_type=video_mp4&rc=NDg4OjlkNzw2PDNnNmllaUBpM2Zwc3A5cnE7OzMzODczNEA2Y2FeL180NWMxYDYtNjBeYSNzaWA0MmQ0X3NhLS1kMTFzcw%3D%3D&vvpl=1&l=202607131529572C479AB591AA160A8B01&btag=e00088000",
    "carousel_urls": [],
    "format": "TikTok",
    "caption": "We went back for more after filming\u2026 #PR #DonQuijote #JONETZ #JapanTravelSouvenirs #AkihabaraDonki Don Quijote operates over 600 stores in Japan, including more than 50 in Tokyo alone. Donki is effectively a one-stop shop. You can find discounted designer goods, skincare and makeup, electronics accessories, high-end wagyu beef, and one of the world's largest selections of cosplay supplies. Donki also offers tax-free shopping for international visitors, allowing you to easily process refunds directly in-store. Open 24 hours, it's a place to experience Japanese culture, offering everything from classic Japanese souvenirs to unique items! Get great coupons here > https://japanportal.donki-global.com/coupon/?ptcd=0000011201",
    "timestamp": "2026-06-26T14:01:32+00:00",
    "likes": 9121,
    "comments": 34,
    "shares": 169,
    "views": 99434,
    "saves": 1353,
    "music": "original sound - hito.bito",
    "audio_song": "original sound - hito.bito",
    "audio_artist": "Megan and Ben",
    "audio_id": "7655704018826038037",
    "audio_is_original": true,
    "engagement": 9324,
    "trendScore": 9.4,
    "velocity": 5828,
    "ageDays": 17.1,
    "source": "keyword:travel film",
    "isNewAccount": true
  },
  {
    "platform": "tiktok",
    "account": "vulamquayphim",
    "url": "https://www.tiktok.com/@vulamquayphim/video/7659248352340610324",
    "thumbnail": "https://p16-common-sign.tiktokcdn-us.com/tos-alisg-p-0037/o8A7EiFWukYvBHBAdlQaLFEAALysB1ByAIiPd~tplv-tiktokx-cropcenter:500:800.jpeg?biz_tag=musically_video.video_cover&dr=9638&idc=useast5&ps=13740610&refresh_token=8c0b2f59&shcp=9b759fb9&shp=c1333099&t=4d5b0474&x-expires=1783976400&x-signature=yNo7NWiDGGvJFOML1kE9dkAeGdk%3D",
    "video": "https://v19.tiktokcdn-us.com/251e69406dfd57d17907f4969d7a30c7/6a5558e5/video/tos/alisg/tos-alisg-pve-0037c001/oMOwjFVIEICQAplgjWfdyHfAjP3oUDoFDgNeCx/?a=1233&bti=NEBzNTY6QGo6OjZALnAjNDQuYCMxNDNg&&bt=1501&ft=gKfIn8s6oA-O12NvgPZZzIxRW-jyO3_45SY&mime_type=video_mp4&rc=ZmlkMzk3aTtkZDtpaTxlOUBpamtlaHI5cmlrPDMzODczNEA2LjQzXi1fXl8xYS9hYjJiYSNwLXAyMmRzazJhLS1kMTFzcw%3D%3D&vvpl=1&l=202607131529544A102FF5115A2A0AEC78&btag=e000b0000",
    "carousel_urls": [],
    "format": "TikTok",
    "caption": "L\u1ea7n \u0111\u1ea7u tr\u1ea3i nghi\u1ec7m Insta360 Luna v\u00e0 n\u00f3 v\u01b0\u1ee3t k\u1ef3 v\u1ecdng c\u1ee7a m\u00ecnh. Nh\u1ecf g\u1ecdn, quay \u0111\u1eb9p, mang \u0111i \u0111\u00e2u c\u0169ng ti\u1ec7n. #Insta360Luna #Insta360 #Luna #Cinematic #Travel",
    "timestamp": "2026-07-06T03:15:34+00:00",
    "likes": 25757,
    "comments": 204,
    "shares": 3462,
    "views": 324365,
    "saves": 3743,
    "music": "original sound - vulamquayphim",
    "audio_song": "original sound - vulamquayphim",
    "audio_artist": "V\u0169 L\u00e0m Quay Phim \ud83c\udfa5",
    "audio_id": "7659248398403062546",
    "audio_is_original": true,
    "engagement": 29423,
    "trendScore": 9.1,
    "velocity": 43191,
    "ageDays": 7.5,
    "source": "keyword:cinematic travel",
    "isNewAccount": true
  },
  {
    "platform": "tiktok",
    "account": "gabmntoya",
    "url": "https://www.tiktok.com/@gabmntoya/video/7658351179574807816",
    "thumbnail": "https://p19-common-sign.tiktokcdn-us.com/tos-alisg-p-0037/oAIDu1MwXAPvjtfeAj7IAEPIGy3hAoA8AU9teQ~tplv-tiktokx-cropcenter:500:800.jpeg?biz_tag=musically_video.video_cover&dr=9638&idc=useast8&ps=13740610&refresh_token=504e3e1e&shcp=9b759fb9&shp=c1333099&t=4d5b0474&x-expires=1783976400&x-signature=lcbYhVbZre12h0dw2RfRqCjoZRA%3D",
    "video": "https://v16m.tiktokcdn-us.com/c6a94cee611ff8f59026c1b6af85e3bf/6a5558f7/video/tos/alisg/tos-alisg-pve-0037c001/oI2Pj9KmUQoCIGD02CjL1qPIIVGgUDAvtAef8f/?a=1233&bti=NEBzNTY6QGo6OjZALnAjNDQuYCMxNDNg&&bt=380&ft=gKfIn8QLodzR12NvkwZZzIxRMQz_XF_45SY&mime_type=video_mp4&rc=Ozk6M2Y0aTVpPGkzZjc3ZUBpanVlbXc5cnd4PDMzODczNEBjL15fLjEuXy0xYDUtL2FgYSMvY3EvMmRrZzBhLS1kMTFzcw%3D%3D&vvpl=1&l=20260713153008E95C0398557BBB07FC19&btag=e000b8000",
    "carousel_urls": [],
    "format": "TikTok",
    "caption": "Straight out of camera photos with the Sony A6400 & Sony 16-50mm kit lens. #sony #a6400 #travelphotography #cinematic #sooc",
    "timestamp": "2026-07-03T17:14:01+00:00",
    "likes": 7733,
    "comments": 77,
    "shares": 321,
    "views": 89732,
    "saves": 1535,
    "music": "her garden",
    "audio_song": "her garden",
    "audio_artist": "Amory Reel",
    "audio_id": "7349310098693343234",
    "audio_is_original": false,
    "engagement": 8131,
    "trendScore": 9.1,
    "velocity": 9038,
    "ageDays": 9.9,
    "source": "keyword:cinematic photography",
    "isNewAccount": true
  },
  {
    "platform": "tiktok",
    "account": "julescinefilms",
    "url": "https://www.tiktok.com/@julescinefilms/video/7656246170171231520",
    "thumbnail": "https://p19-common-sign.tiktokcdn-us.com/tos-useast2a-p-0037-euttp/owZB0xaAAXuY2FxagViBYkyyIPHhcBMIEPiGt~tplv-tiktokx-cropcenter:500:800.jpeg?biz_tag=musically_video.video_cover&dr=9638&idc=useast5&ps=13740610&refresh_token=e7eb3ab8&shcp=9b759fb9&shp=c1333099&t=4d5b0474&x-expires=1783976400&x-signature=NOlUKbmIaV91q7mRiTUgjx4NO28%3D",
    "video": "https://v45.tiktokcdn-us.com/8b76a4f17bb1080ceb52d0012b2ac5a9/6a5558f3/video/tos/useast2a/tos-useast2a-ve-0068-euttp/oEewAepAGgDIQfgqF0GkMUIsgQFVE5jjOLuIS4/?a=1233&bti=NEBzNTY6QGo6OjZALnAjNDQuYCMxNDNg&&bt=1422&ft=aEKfuqT0mI2PD125QqqI3wUThrlcMeF~O5&mime_type=video_mp4&rc=MzszZ2VnZGU1OTVmZDM7aUBpamxqZWs5cmc6PDMzZjczNUBiNDU0MS0yXzIxMzIuYDFgYSNfc2VhMmQ0Mi1hLS1kMTNzcw%3D%3D&vvpl=1&l=20260713153011635B46952589FA099C73&btag=e000bd000",
    "carousel_urls": [],
    "format": "TikTok",
    "caption": "live. your. life. #cinematic #filmmaking",
    "timestamp": "2026-06-28T01:05:34+00:00",
    "likes": 7280,
    "comments": 12,
    "shares": 201,
    "views": 88306,
    "saves": 519,
    "music": "This Is The Life",
    "audio_song": "This Is The Life",
    "audio_artist": "Amy Macdonald",
    "audio_id": "6937182500980541442",
    "audio_is_original": false,
    "engagement": 7493,
    "trendScore": 8.5,
    "velocity": 5660,
    "ageDays": 15.6,
    "source": "keyword:travel filmmaker",
    "isNewAccount": true
  },
  {
    "platform": "tiktok",
    "account": "_lecons",
    "url": "https://www.tiktok.com/@_lecons/video/7655700544996003079",
    "thumbnail": "https://p19-common-sign.tiktokcdn-us.com/tos-alisg-p-0037/oMxeRqAdPB8EEgA8BAQAWoMfbbtgAFIDAAUCAo~tplv-tiktokx-cropcenter:500:800.jpeg?biz_tag=musically_video.video_cover&dr=9638&idc=useast5&ps=13740610&refresh_token=f12c4fc7&shcp=9b759fb9&shp=c1333099&t=4d5b0474&x-expires=1783976400&x-signature=DeINx5o%2BcmbtjnJO%2BewDIRD1JHU%3D",
    "video": "https://v16m.tiktokcdn-us.com/f7c079d0627906517ab06f92a9240df1/6a5559b8/video/tos/alisg/tos-alisg-pve-0037c001/o4RiKVQAQDAFyEPhxqGznffsyeDwGFzIJhMoEe/?a=1233&bti=NEBzNTY6QGo6OjZALnAjNDQuYCMxNDNg&&bt=2089&ft=gKfIn8buoTfR12NvHPZZzIxRl7PhZQ_45SY&mime_type=video_mp4&rc=aTdlOzk6aTg1aDw2N2Q8NEBpanM3OG05cjg6OzMzODczNEA1XmJfNF41XjAxMDUuYDBiYSNwNmZlMmRjc3NhLS1kMTFzcw%3D%3D&vvpl=1&l=202607131529572C479AB591AA160A8B01&btag=e00098000",
    "carousel_urls": [],
    "format": "TikTok",
    "caption": "On Sunday 21 June at 10:19 I was trail running near Valbon\u00eb in Albania when I was bitten by a European Nose-horned Viper. Here is a summarised snapshot of the events that followed with time stamps. I\u2019ve been living in New Zealand the last 3.5 years so my knowledge of snakebite first aid in the moment was slightly hazy. I instantly filmed the snake for identification purposes, sat down on the trail and dialled 112 as this was the only line that I was able to call with my eSIM. Having no success with the operator and after they hung up on me, I called my dad in Australia who asked for my What3Words to give to Australian emergency services for Interpol. I then called a hostel owner in Shkod\u00ebr who was able to assist by putting me in contact with local emergency authorities on WhatsApp (thank goodness for cell service) who gained my current location and dispatched an ambulance. In the meantime, I initially removed my socks and singlet to create a makeshift tourniquet higher up on the limb but realised this was incorrect action and later removed this to provide compression around the area of the bite. I had been informed to stay immobilised, despite being on a section of a trail that would be tricky to reach.  Without cell service, this could have been a completely different outcome. Please travel with an inReach or PLB if you intend to be entering areas without internet coverage. Also download an emergency locator app like What3Words and always carry an appropriate first aid kit.  #snakebite #albania #valbon\u00eb #trailrunning #solobackpacking",
    "timestamp": "2026-06-26T13:48:14+00:00",
    "likes": 1346834,
    "comments": 10317,
    "shares": 89454,
    "views": 17414639,
    "saves": 57942,
    "music": "original sound - _lecons",
    "audio_song": "original sound - _lecons",
    "audio_artist": "Amy",
    "audio_id": "7655700918900083474",
    "audio_is_original": true,
    "engagement": 1446605,
    "trendScore": 8.3,
    "velocity": 1020154,
    "ageDays": 17.1,
    "source": "keyword:travel film",
    "isNewAccount": true
  },
  {
    "platform": "tiktok",
    "account": "phillip3s",
    "url": "https://www.tiktok.com/@phillip3s/video/7654466983198592270",
    "thumbnail": "https://p16-common-sign.tiktokcdn-us.com/tos-useast5-p-85c255-tx/ooxpKbBeII57eI8HEQUg0GqCdQpMksseAJzLBD~tplv-tiktokx-cropcenter:500:800.jpeg?biz_tag=musically_video.video_cover&dr=9638&idc=useast8&ps=13740610&refresh_token=c488e8ff&shcp=9b759fb9&shp=c1333099&t=4d5b0474&x-expires=1783976400&x-signature=aiGAkR5LxL3rpSfYeZpCJ5XN4YM%3D",
    "video": "https://v16m.tiktokcdn-us.com/81969e7ed6fbf4ad7e2a1a069c1d1626/6a555900/video/tos/useast5/tos-useast5-v-85c255-tx/ocwISEIpgEFoD5tcBFfmiqDBkHOZfEw2WAdUQ6/?a=1233&bti=NEBzNTY6QGo6OjZALnAjNDQuYCMxNDNg&&bt=2651&ft=gKfIn8s6oA-O12Nv~wZZzIxRPh-z93_45SY&mime_type=video_mp4&rc=OGUzNzY3aTg4aTZlNzU8NUBpamh1ZnA5cm81OzQzZzM2NEAvXi8vMzJeNWIxLi0zNC1hYSNjam1yMmQ0L3FhLS1kLS9zcw%3D%3D&vvpl=1&l=2026071315301886F48511E56A5F066C01&btag=e000f8000",
    "carousel_urls": [],
    "format": "TikTok",
    "caption": "Don\u2019t ruin your experience believing what the media portrays \u2665\ufe0f Follow for more Socotra Content! \ud83c\uddfe\ud83c\uddea Visiting this place has been one of the most eye opening experiences in my life. Seeing the people of Socotra so happy with so little makes you feel so blessed. These people never asked for money or anything just wanted real connection \u2665\ufe0f traveling like this is really what makes you into a different person. Book with #travel #socotra #yemen #adventure #cinematography",
    "timestamp": "2026-06-23T06:01:56+00:00",
    "likes": 3632,
    "comments": 118,
    "shares": 160,
    "views": 63296,
    "saves": 258,
    "music": "original sound - phillip3s",
    "audio_song": "original sound - phillip3s",
    "audio_artist": "Phillip Pham | Travel Creator",
    "audio_id": "7654467166376299277",
    "audio_is_original": true,
    "engagement": 3910,
    "trendScore": 6.2,
    "velocity": 3103,
    "ageDays": 20.4,
    "source": "keyword:travel cinematography",
    "isNewAccount": true
  },
  {
    "platform": "tiktok",
    "account": "populartravel",
    "url": "https://www.tiktok.com/@populartravel/video/7658826165892680993",
    "thumbnail": "https://p16-common-sign.tiktokcdn-us.com/tos-useast2a-p-0037-euttp/owEIFXIQmvAFyEZOCfR67SfgA3DUDCAQbA6qLT~tplv-tiktokx-cropcenter:500:800.jpeg?biz_tag=musically_video.video_cover&dr=9638&idc=useast5&ps=13740610&refresh_token=c1e5ee5f&shcp=9b759fb9&shp=c1333099&t=4d5b0474&x-expires=1783976400&x-signature=fjzVnnopRre2hExOtjL5oAMKbBo%3D",
    "video": "https://v19.tiktokcdn-us.com/b754b5883ed0024122060a8d289d3034/6a555924/video/tos/useast2a/tos-useast2a-ve-0068c001-euttp/okcMhZopxikCrUJ1A2QwEnIJf6CxiABz7B0IJi/?a=1233&bti=NEBzNTY6QGo6OjZALnAjNDQuYCMxNDNg&&bt=2147&ft=gKfIn8buoTfR12NvHPZZzIxRl7PhZQ_45SY&mime_type=video_mp4&rc=aDMzOTg0OjdpPDRnNmk0O0BpM3U4bG45cmhzPDMzZjczNUBhYV5iLzZhNjIxMDJgNWI0YSNvZ2JpMmRjbjFhLS1kMTNzcw%3D%3D&vvpl=1&l=202607131529572C479AB591AA160A8B01&btag=e00090000",
    "carousel_urls": [],
    "format": "TikTok",
    "caption": "\ud83c\uddee\ud83c\uddf3 India Is More Incredible Than You Think!#india #indianarmy #indiatravel #bollywoodsong #travel",
    "timestamp": "2026-07-04T23:57:12+00:00",
    "likes": 12937,
    "comments": 398,
    "shares": 1670,
    "views": 244016,
    "saves": 1400,
    "music": "original sound - populartravel",
    "audio_song": "original sound - populartravel",
    "audio_artist": "populartravel",
    "audio_id": "7658826204090321697",
    "audio_is_original": true,
    "engagement": 15005,
    "trendScore": 6.1,
    "velocity": 28217,
    "ageDays": 8.6,
    "source": "keyword:travel film",
    "isNewAccount": true
  },
  {
    "platform": "tiktok",
    "account": "travelvlog018",
    "url": "https://www.tiktok.com/@travelvlog018/video/7657099641653038358",
    "thumbnail": "https://p16-common-sign.tiktokcdn-us.com/tos-no1a-p-0037-no/o4RGN8gQfAIWytC8DDRqM5BGeEFkFEwIr3zQr7~tplv-tiktokx-cropcenter:500:800.jpeg?biz_tag=musically_video.video_cover&dr=9638&idc=useast8&ps=13740610&refresh_token=5ff3cba2&shcp=9b759fb9&shp=c1333099&t=4d5b0474&x-expires=1783976400&x-signature=p3po4jqOaHUdrCMQoqXD5agzeQU%3D",
    "video": "https://v16m.tiktokcdn-us.com/1c29387097103ea073bff1c2870ba352/6a55591b/video/tos/no1a/tos-no1a-ve-0068c001-no/oQ4WfGagMaLvLkbeIA3GYIU7eqjRhAo4IRiDAd/?a=1233&bti=NEBzNTY6QGo6OjZALnAjNDQuYCMxNDNg&&bt=941&ft=gKfIn8QLodzR12NvkwZZzIxRMQz_XF_45SY&mime_type=video_mp4&rc=NzZlaTdnO2k5NjM8PDlnZkBpang1c3c5cm1xPDMzbzczNUA2X2I0Yy40NWMxLTRgLzMxYSMuNWVuMmRjai5hLS1kMTFzcw%3D%3D&vvpl=1&l=20260713153008E95C0398557BBB07FC19&btag=e00088000",
    "carousel_urls": [],
    "format": "TikTok",
    "caption": "Here is how to get that high end cinematic photos with phone.\ud83c\udf08\ud83d\udc45#photographerlife #photographytips #photography",
    "timestamp": "2026-06-30T08:17:26+00:00",
    "likes": 366405,
    "comments": 2376,
    "shares": 16116,
    "views": 6900656,
    "saves": 50136,
    "music": "Faded (Dash Berlin Remix)",
    "audio_song": "Faded (Dash Berlin Remix)",
    "audio_artist": "Alan Walker",
    "audio_id": "6716968952053893122",
    "audio_is_original": false,
    "engagement": 384897,
    "trendScore": 5.6,
    "velocity": 518833,
    "ageDays": 13.3,
    "source": "keyword:cinematic photography",
    "isNewAccount": true
  },
  {
    "platform": "tiktok",
    "account": "withathenaofficial",
    "url": "https://www.tiktok.com/@withathenaofficial/video/7659053411979070741",
    "thumbnail": "https://p19-common-sign.tiktokcdn-us.com/tos-alisg-p-0037/oMAKBAwU3nvEgksipLICiBYbBAIaAiksUBIAE~tplv-tiktokx-cropcenter:500:800.jpeg?biz_tag=musically_video.video_cover&dr=9638&idc=useast5&ps=13740610&refresh_token=c703af67&shcp=9b759fb9&shp=c1333099&t=4d5b0474&x-expires=1783976400&x-signature=9KdNnbNar1NwymX6urdsx1Bj3FY%3D",
    "video": "https://v19.tiktokcdn-us.com/423b706457e0d88efd788a451bc8dee2/6a555908/video/tos/alisg/tos-alisg-pve-0037c001/oE3U7ggISjjigIlQuCLUA2aGAe4KaDfheNlIpw/?a=1233&bti=NEBzNTY6QGo6OjZALnAjNDQuYCMxNDNg&&bt=2116&ft=gKfIn8buoTfR12NvHPZZzIxRl7PhZQ_45SY&mime_type=video_mp4&rc=aTNlaDw5O2Y2aGdpaTg3OEBpanc1NXY5cjo5PDMzODczNEA2MC5gX2AuNjExXjQyLjFgYSNzaDQxMmRjbDJhLS1kMWBzcw%3D%3D&vvpl=1&l=202607131529572C479AB591AA160A8B01&btag=e00088000",
    "carousel_urls": [],
    "format": "TikTok",
    "caption": "POV: You got to be a princess for a day in Japan. \ud83d\udc51\u2728 If you\u2019ve ever dreamed of dressing up like royalty, this is your chance. At the Music Forest Museum in Kawaguchiko, you can rent from a huge selection of elegant dresses (they even have outfits for little princes and princesses!) and wander through a fairytale-like village filled with beautiful photo spots. If you\u2019re lucky with the weather, you\u2019ll even have Mt. Fuji as the backdrop! \ud83d\uddfb While you\u2019re there, don\u2019t miss the Titanic Exhibition, now extended until December 31. It includes beautiful displays, an opera performance inspired by the film, and it\u2019s definitely worth adding to your visit. \ud83d\udccdKawaguchiko Music Forest Museum, Yamanashi \u26a0\ufe0f Travel can get expensive fast, so I always take whatever discounts I can get! Feel free to use my Klook code \ud835\uddea\ud835\udddc\ud835\udde7\ud835\udddb\ud835\uddd4\ud835\udde7\ud835\udddb\ud835\uddd8\ud835\udde1\ud835\uddd4 when you book your hotels + transpo + other activ#kawaguchiko#kawaguchikoprincess #dress",
    "timestamp": "2026-07-05T14:39:00+00:00",
    "likes": 10050,
    "comments": 61,
    "shares": 3750,
    "views": 266079,
    "saves": 5719,
    "music": "Uplifting Classical Orchestral - Full Length",
    "audio_song": "Uplifting Classical Orchestral - Full Length",
    "audio_artist": "pinegroove",
    "audio_id": "7449250197216380965",
    "audio_is_original": false,
    "engagement": 13861,
    "trendScore": 5.2,
    "velocity": 33113,
    "ageDays": 8.0,
    "source": "keyword:travel film",
    "isNewAccount": true
  },
  {
    "platform": "tiktok",
    "account": "__.adam._",
    "url": "https://www.tiktok.com/@__.adam._/video/7655438273522732302",
    "thumbnail": "https://p16-common-sign.tiktokcdn-us.com/tos-useast5-p-0068-tx/og1yJeAFjIO1bSuoAeEJIlI9eWRcMFOITGXGeL~tplv-tiktokx-cropcenter:500:800.jpeg?biz_tag=musically_video.video_cover&dr=9638&idc=useast5&ps=13740610&refresh_token=f0c8bb85&shcp=9b759fb9&shp=c1333099&t=4d5b0474&x-expires=1783976400&x-signature=cAvCibc6TEjpoN3B7Lx0hH445Es%3D",
    "video": "https://v16m.tiktokcdn-us.com/8303d825fcf381dd86a888dd27fd12ca/6a55592f/video/tos/useast5/tos-useast5-ve-0068c003-tx/o0bIRlTuOGlejIe9SeL8AWEIGAXaQJ1eRSFoLy/?a=1233&bti=NEBzNTY6QGo6OjZALnAjNDQuYCMxNDNg&&bt=1657&ft=gKfIn8buoTfR12NvHPZZzIxRl7PhZQ_45SY&mime_type=video_mp4&rc=MztnM2loaDNkOzhoNzk0ZEBpMzw2aG85cnBzOzMzZzczNEAtLmFhNV5eXjIxM2AtYzQwYSNzcnFvMmRrMnJhLS1kMS9zcw%3D%3D&vvpl=1&l=202607131529572C479AB591AA160A8B01&btag=e00090000",
    "carousel_urls": [],
    "format": "TikTok",
    "caption": "Finally got the vlog up (almost a month after I filmed it \ud83d\ude05) #travel #Vlog #nyc #couple #marriage @Briel Adams-Wheatley",
    "timestamp": "2026-06-25T20:50:34+00:00",
    "likes": 130174,
    "comments": 616,
    "shares": 1746,
    "views": 2613689,
    "saves": 2249,
    "music": "Vlog",
    "audio_song": "Vlog",
    "audio_artist": "wouldliker",
    "audio_id": "7501680481626785808",
    "audio_is_original": false,
    "engagement": 132536,
    "trendScore": 5.1,
    "velocity": 147023,
    "ageDays": 17.8,
    "source": "keyword:travel film",
    "isNewAccount": true
  },
  {
    "platform": "tiktok",
    "account": "zee42867",
    "url": "https://www.tiktok.com/@zee42867/video/7659259564973395220",
    "thumbnail": "https://p16-common-sign.tiktokcdn-us.com/tos-alisg-p-0037/oEIWQABARUaSAgDqIFCufCfYKg4EEEAgUuyACn~tplv-tiktokx-cropcenter:500:800.jpeg?biz_tag=musically_video.video_cover&dr=9638&idc=useast8&ps=13740610&refresh_token=e377ac5e&shcp=9b759fb9&shp=c1333099&t=4d5b0474&x-expires=1783976400&x-signature=hltBVwdvaxNbRXxr%2FCMTS5I2pbc%3D",
    "video": "https://v16m.tiktokcdn-us.com/31549abbfd07a8cb78b803f349365e5b/6a5558fe/video/tos/alisg/tos-alisg-pve-0037c001/o81Jh9RKEQZmAPUCIiELVAAzQIiBEqfrTwCBPi/?a=1233&bti=NEBzNTY6QGo6OjZALnAjNDQuYCMxNDNg&&bt=1201&ft=gKfIn8QLodzR12NvkwZZzIxRMQz_XF_45SY&mime_type=video_mp4&rc=Zzk8NTpoZmdmZzQ4ZWk2OkBpM2s7ZHc5cmtsPDMzODczNEBfNV41NjIxXmIxNGEwXzE1YSNncmxeMmRjYzJhLS1kMTFzcw%3D%3D&vvpl=1&l=20260713153008E95C0398557BBB07FC19&btag=e000b8000",
    "carousel_urls": [],
    "format": "TikTok",
    "caption": "#capcut #capcutpioneer #capcutnow  Hunsha AI Prewedding Photo Prompt ay tumutulong na gawing cinematic luxury wedding portrait ang iyong ordinaryong photos nang napakadali \ud83d\udc8d\ud83d\udcf8 Gamit ang Gemini AI, Dreamina, Hypic at CapCut maaari kang gumawa ng sparkling princess wedding dress look at professional cinematic prewedding photoshoot vibe. Kahit simpleng photo lang ay puwedeng gawing romantic, elegant at luxury bridal portrait gamit ang AI wedding filter effect \u2728 Turn your ordinary photos into cinematic AI wedding and prewedding portraits instantly with luxury bridal atmosphere and princess wedding dress style. Gemini AI prewedding photo prompt \u1000\u102d\u102f \u1021\u101e\u102f\u1036\u1038\u1015\u103c\u102f\u1015\u103c\u102e\u1038 wedding dress girl portrait, luxury bridal photos, couple wedding photos, romantic cinematic prewedding scene \u1010\u103d\u1031\u1000\u102d\u102f realistic high-end weAI Prewedding Photo Prompt ay tumutulong na gawing cinematic luxury wedding portrait ang iyong ordinaryong photos nang napakadali \ud83d\udc8d\ud83d\udcf8 Gamit ang Gemini AI, Dreamina, Hypic at CapCut maaari kang gumawa ng sparkling princess wedding dress look at professional cinematic prewedding photoshoot vibe. Kahit simpleng photo lang ay puwedeng gawing romantic, elegant at luxury bridal portrait gamit ang AI wedding filter effect \u2728 Turn your ordinary photos into cinematic AI wedding and prewedding portraits instantly with luxury bridal atmosphere and princess wedding dress style. Gemini AI prewedding photo prompt \u1000\u102d\u102f \u1021\u101e\u102f\u1036\u1038\u1015\u103c\u102f\u1015\u103c\u102e\u1038 wedding dress girl portrait, luxury bridal photos, couple wedding photos, romantic cinematic prewedding scene \u1010\u103d\u1031\u1000\u102d\u102f realistic high-end wedding photography quality \u1014\u1032\u1037 \u1016\u1014\u103a\u1010\u102e\u1038\u1014\u102d\u102f\u1004\u103a\u1015\u102b\u1010\u101a\u103a Create stunning luxury wedding portraits using Gemini AI wedding photo prompts with sparkling wedding dress texture and cinematic lighting. \u1019\u103b\u1000\u103a\u1014\u103e\u102c\u1000\u102d\u102f \u1019\u1015\u103c\u1031\u102c\u1004\u103a\u1038\u101c\u1032\u1018\u1032 (No face change) AI \u1000 lighting, skin tone, sparkle wedding dress texture, bridal details, background atmosphere \u1000\u102d\u102f\u1015\u1032 enhance \u101c\u102f\u1015\u103a\u1015\u1031\u1038\u1015\u103c\u102e\u1038 natural cinematic wedding photography look \u1000\u102d\u102f \u1016\u1014\u103a\u1010\u102e\u1038\u1015\u1031\u1038\u1015\u102b\u1010\u101a\u103a No face change \u2014 only lighting, color grading, wedding dress sparkle, and luxury wedding atmosphere enhancement. \u1012\u102e AI wedding trend \u1000 \u2022 Prewedding photos \u2022 Wedding dress princess portrait \u2022 Couple wedding photos \u2022 Luxury bridal photos \u2022 Cinematic wedding portrait \u2022 TikTok / Reels / Facebook wedding content \u1021\u1010\u103d\u1000\u103a \u1021\u1011\u1030\u1038\u101e\u1004\u1037\u103a\u1010\u1031\u102c\u103a\u1015\u102b\u1010\u101a\u103a \ud83d\udd25 This viral AI wedding photo trend is perfect for girls, couples, bridal creators, and wedding content creators across Southeast Asia and global AI photo communities. \u101c\u102f\u1015\u103a\u1014\u100a\u103a\u1038 (How to create AI wedding photos): Gemini AI / Dreamina / Hypic / CapCut \u1011\u1032\u1000\u102d\u102f\u101d\u1004\u103a\u1015\u102b Prewedding template \u101e\u102d\u102f\u1037\u1019\u101f\u102f\u1010\u103a AI wedding prompt \u1000\u102d\u102f\u101b\u103d\u1031\u1038\u1015\u102b Photo upload \u101c\u102f\u1015\u103a\u1015\u102b Generate \u1000\u102d\u102f\u1014\u103e\u102d\u1015\u103a\u1015\u102b Cinematic luxury AI wedding portrait \u1000\u102d\u102f \u1001\u103b\u1000\u103a\u1001\u103b\u1004\u103a\u1038\u101b\u101b\u103e\u102d\u1014\u102d\u102f\u1004\u103a\u1015\u102b\u1010\u101a\u103a \u2728 No professional editing skills needed \u2014 anyone can create stunning AI wedding photos easily. AI Wedding Photo Prompt & SEO Keywords (Traffic Boost): ai prewedding photo prompt ai wedding photo prompt gemini ai wedding photo prompt gemini ai prewedding photo prompt ai wedding dress photo generator ai princess wedding dress generator ai bridal portrait generator ai luxury bridal photo generator ai cinematic wedding portrait ai couple wedding photo generator ai wedding photoshoot generator ai prewedding photo tutorial ai wedding photo tutorial ai wedding filter effect tutorial Dreamina wedding photo tutorial CapCut wedding template tutorial Hypic wedding photo edit tutorial ai prewedding photo templates ai bridal photo generator ai wedding portrait generator ai luxury wedding photography generator ai wedding photo trend ai bridal portrait trend ai prewedding trend tutorial gemini ai \u101c\u1000\u103a\u1011\u1015\u103a\u1013\u102c\u1010\u103a\u1015\u102f\u1036 prompt ai \u1019\u1004\u103a\u1039\u1002\u101c\u102c\u1006\u1031\u102c\u1004\u103a\u1015\u102f\u1036\u101c\u102f\u1015\u103a\u1014\u100a\u103a\u1038 ai \u1019\u1004\u103a\u1039\u1002\u101c\u102c\u1000\u103c\u102d\u102f\u1013\u102c\u1010\u103a\u1015\u102f\u1036\u101c\u102f\u1015\u103a\u1014\u100a\u103a\u1038 ai wedding dress photo \u101c\u102f\u1015\u103a\u1014\u100a\u103a\u1038 ai princess wedding dress portrait \u101c\u102f\u1015\u103a\u1014\u100a\u103a\u1038 ai couple wedding portrait \u101c\u102f\u1015\u103a\u1014\u100a\u103a\u1038 ai bridal portrait tutorial ai prewedding photo tutorial for girls #fyp #wedding",
    "timestamp": "2026-07-06T03:59:03+00:00",
    "likes": 9381,
    "comments": 235,
    "shares": 15632,
    "views": 525251,
    "saves": 1161,
    "music": "original sound - markimfanexpire",
    "audio_song": "original sound - markimfanexpire",
    "audio_artist": "markimfanexpire",
    "audio_id": "7301707485268724482",
    "audio_is_original": true,
    "engagement": 25248,
    "trendScore": 4.8,
    "velocity": 70223,
    "ageDays": 7.5,
    "source": "keyword:cinematic photography",
    "isNewAccount": true
  },
  {
    "platform": "tiktok",
    "account": "travelwithhasanalikhan",
    "url": "https://www.tiktok.com/@travelwithhasanalikhan/video/7655598024273464598",
    "thumbnail": "https://p16-common-sign.tiktokcdn-us.com/tos-no1a-p-0037-no/oMlEFAfDkI2zVrqC0SoaBPWi8CkAeEUAFAAkQg~tplv-tiktokx-cropcenter:500:800.jpeg?biz_tag=musically_video.video_cover&dr=9638&idc=useast5&ps=13740610&refresh_token=d1d1c402&shcp=9b759fb9&shp=c1333099&t=4d5b0474&x-expires=1783976400&x-signature=9DgpWdyJvZrynaudDwKHQyjX8Ss%3D",
    "video": "https://v45.tiktokcdn-us.com/17154d9ea16b3009e035be071f7b2ed1/6a555921/video/tos/no1a/tos-no1a-ve-0068c001-no/o8G44gTfRMheogIPfetlSeRsHRRoJA6gAhAjLR/?a=1233&bti=NTY6QGo0QHM6OjZANDQuYCMucCMxNDNg&&bt=1195&ft=aEKfuqT0mI2PD125QqqI3wUThrlcMeF~O5&mime_type=video_mp4&rc=OjpnaDc5Zjw5aTQ4NzNnNUBpM3g7OW45cjo1OzMzbzgzNUAyLTBhMDMyXmExYGA0NmM1YSNpZC5gMmRzXnNhLS1kLzFzcw%3D%3D&vvpl=1&l=20260713153011635B46952589FA099C73&btag=e00095000",
    "carousel_urls": [],
    "format": "TikTok",
    "caption": "\ud83d\udccdLahore Series Part 2 | The Soul of the Walled City \u2764\ufe0f\ud83c\udff0** Welcome back to the Lahore Series! In Part 2, we explore the timeless culture, rich traditions, and fascinating history hidden inside the streets of the Walled City. From centuries-old architecture to the stories behind Lahore's iconic gates, this journey reveals why Lahore is known as the heart of Pakistan. If you love travel, history, culture, and cinematic storytelling, this series is made for you. Follow for more episodes as we uncover the hidden gems, historical landmarks, local food, and unforgettable stories of Lahore. #Lahore #TravelPakistan #ExploreLahore #LahoreSeries #LahoreHistory #WalledCityLahore #ExploreLahore #LahoreCulture #VisitLahore #PakistanTravel #TravelPakistan #HistoricalPakistan #HeritagePakistan #CulturalHeritage #HistoricPlaces #TravelVlog #TravelCreator #TravelContent #PakistanTourism #HistoryLovers #CultureTrip #HiddenPakistan #LahoreOldCity #OldLahore #ArchitectureLovers #Storytelling #TravelFilmmaking #CinematicTravel #DiscoverPakistan #TravelReels #tiktoktravel #ExplorePakistan #TravelTok",
    "timestamp": "2026-06-26T09:00:00+00:00",
    "likes": 6027,
    "comments": 38,
    "shares": 151,
    "views": 138252,
    "saves": 677,
    "music": "original sound - travelwithhasanalikhan",
    "audio_song": "original sound - travelwithhasanalikhan",
    "audio_artist": "travelwithhasanalikhan",
    "audio_id": "7655598094402194198",
    "audio_is_original": true,
    "engagement": 6216,
    "trendScore": 4.5,
    "velocity": 8004,
    "ageDays": 17.3,
    "source": "keyword:travel filmmaker",
    "isNewAccount": true
  },
  {
    "platform": "tiktok",
    "account": "lifeinframes.ava",
    "url": "https://www.tiktok.com/@lifeinframes.ava/video/7655033677398805773",
    "thumbnail": "https://p16-common-sign.tiktokcdn-us.com/tos-useast5-p-0068-tx/o8CqC4PAExWFsBSAxgfIPIRARSPMDDAgEfKQOS~tplv-tiktokx-origin.image?biz_tag=musically_video.video_cover&dr=8593&idc=useast5&ps=933b5bde&refresh_token=f4cedc2e&s=SEARCH&sc=cover&shcp=c1333099&shp=d05b14bd&t=bacd0480&x-expires=1784041200&x-signature=lmuRjp0r3ufJ%2Br7hsnHc6NtbHho%3D",
    "video": "https://v16m.tiktokcdn-us.com/7638f9208a15b09803810c5d8aa498ea/6a5558fd/video/tos/useast5/tos-useast5-ve-0068c003-tx/owXEWGehIAIFE1gRhOSIhVMEeQpGA4L0o4Fe2e/?a=1233&bti=NEBzNTY6QGo6OjZALnAjNDQuYCMxNDNg&&bt=902&ft=BIcq8V~3wUxl7K2gUtIvk84jWLpi0L~~QjKJfa5hgG0P3-I&mime_type=video_mp4&rc=OTs6NDY5ZGk0OzhkaWRkPEBpanQ7bXI5cjM1OzMzZzczNEBiXmE2Ll5hX2ExLi1eLjFgYSNxaW81MmRrMHJhLS1kMS9zcw%3D%3D&vvpl=1&l=20260713153015F8627713AE64650B505C&btag=e000b8000",
    "carousel_urls": [],
    "format": "TikTok",
    "caption": "Not ideal for vlogs, but this lens shines for cinematic B-roll and montages. \ud83e\udd0c \u2728  #fujifilm #cameratok #fujifilmxt30ii #fujifilmxseries #cameratok",
    "timestamp": "2026-06-24T18:40:51+00:00",
    "likes": 1350,
    "comments": 36,
    "shares": 49,
    "views": 34649,
    "saves": 203,
    "music": "original sound - thoroughbreds2017",
    "audio_song": "original sound - thoroughbreds2017",
    "audio_artist": "thoroughbreds2017",
    "audio_id": "7567863571305728775",
    "audio_is_original": true,
    "engagement": 1435,
    "trendScore": 4.1,
    "velocity": 1836,
    "ageDays": 18.9,
    "source": "keyword:cinematic b roll",
    "isNewAccount": true
  },
  {
    "platform": "tiktok",
    "account": "user80276956658057",
    "url": "https://www.tiktok.com/@user80276956658057/video/7655280760605248781",
    "thumbnail": "https://p16-common-sign.tiktokcdn-us.com/tos-useast5-p-0068-tx/oED2AE5AWIBPOFME7S5fA47Y9NAeCRgO9qEQAD~tplv-tiktokx-cropcenter:500:800.jpeg?biz_tag=musically_video.video_cover&dr=9638&idc=useast8&ps=13740610&refresh_token=d906347f&shcp=9b759fb9&shp=c1333099&t=4d5b0474&x-expires=1783976400&x-signature=1waRTjz1WMCluceg8sne9zHhYVo%3D",
    "video": "https://v16m.tiktokcdn-us.com/98a229033c716555a87a7d22e4dc3ec3/6a5558f5/video/tos/useast5/tos-useast5-ve-0068c002-tx/o0iKbHE960dKbtBWAwfuiYApQLIqaCwPBoH1BB/?a=1233&bti=NEBzNTY6QGo6OjZALnAjNDQuYCMxNDNg&&bt=952&ft=gKfIn8QLodzR12NvkwZZzIxRMQz_XF_45SY&mime_type=video_mp4&rc=OjZoOzY4PDgzM2kzZjo7ZEBpM2RnNXQ5cjpqOzMzZzgzNEA2My8tLV9hNV8xXzIxLTEwYSNrYWdgMmRzX3JhLS1kLy9zcw%3D%3D&vvpl=1&l=20260713153008E95C0398557BBB07FC19&btag=e000b8000",
    "carousel_urls": [],
    "format": "TikTok",
    "caption": "#capcut #capcutpioneer \u0647\u0644 \u062a\u0631\u064a\u062f \u0625\u0646\u0634\u0627\u0621 \u0635\u0648\u0631 \u063a\u0627\u0645\u0636\u0629 \u0648\u0641\u0627\u062e\u0631\u0629 \u0645\u062b\u0644 \u0647\u0630\u0647\u061f   \u0623\u0635\u0628\u062d\u062a \u0635\u0648\u0631 Gothic Portrait \u0648 Dark Feminine Style \u0645\u0646 \u0623\u0643\u062b\u0631 \u0627\u0644\u062a\u0631\u0646\u062f\u0627\u062a \u0627\u0646\u062a\u0634\u0627\u0631\u0627\u064b \u0639\u0644\u0649 TikTok! \u2728  \u0647\u0644 \u062a\u0628\u062d\u062b \u0639\u0646 \u0642\u0627\u0644\u0628 \u0645\u062c\u0627\u0646\u064a \u0644\u0625\u0646\u0634\u0627\u0621 \u0635\u0648\u0631 \u0628\u0648\u0631\u062a\u0631\u064a\u0647 \u0627\u062d\u062a\u0631\u0627\u0641\u064a\u0629 \u0628\u0638\u0644\u0627\u0644 \u0627\u0644\u062f\u0627\u0646\u062a\u064a\u0644 \u0627\u0644\u0633\u0648\u062f\u0627\u0621 \u0648\u062a\u0623\u062b\u064a\u0631\u0627\u062a \u0627\u0644\u0636\u0648\u0621 \u0627\u0644\u0633\u064a\u0646\u0645\u0627\u0626\u064a\u0629\u061f  \u0628\u0627\u0633\u062a\u062e\u062f\u0627\u0645 \u0627\u0644\u0630\u0643\u0627\u0621 \u0627\u0644\u0627\u0635\u0637\u0646\u0627\u0639\u064a \u064a\u0645\u0643\u0646\u0643 \u0627\u0644\u0622\u0646 \u0625\u0646\u0634\u0627\u0621 \u0635\u0648\u0631 \u0645\u0630\u0647\u0644\u0629 \u0628\u0623\u0633\u0644\u0648\u0628:  \u2728 Gothic Woman Portrait\u2728 Black Lace Veil Portrait\u2728 Lace Shadow Photography\u2728 Dark Beauty Portrait\u2728 Cinematic Female Portrait\u2728 Mysterious Woman Aesthetic   \u0643\u0644\u0645\u0627\u062a \u0627\u0644\u0628\u062d\u062b \u0627\u0644\u0631\u0627\u0626\u062c\u0629 \u062d\u0627\u0644\u064a\u0627\u064b:  gothic portrait trend\u3001dark feminine ai\u3001black lace veil portrait\u3001lace shadow photography\u3001cinematic beauty template\u3001gothic woman template\u3001luxury portrait ai\u3001portrait ai free\u3001fine art portrait\u3001mysterious woman aesthetic   \u0642\u0627\u0644\u0628 \u0645\u062c\u0627\u0646\u064a \u062c\u0627\u0647\u0632 \u062a\u0631\u0646\u062f \u0627\u0644\u062c\u0645\u0627\u0644 \u0627\u0644\u063a\u0627\u0645\u0636\u2728 \u062a\u0631\u0646\u062f \u0627\u0644\u0628\u0648\u0631\u062a\u0631\u064a\u0647 \u0627\u0644\u0633\u064a\u0646\u0645\u0627\u0626\u064a \u062a\u0631\u0646\u062f \u0627\u0644\u062a\u0635\u0648\u064a\u0631 \u0627\u0644\u0641\u0646\u064a \u0627\u0644\u0641\u0627\u062e\u0631   \u0627\u0636\u063a\u0637 \u0639\u0644\u0649 \u0627\u0644\u0632\u0631 \u0623\u0633\u0641\u0644 \u0627\u0644\u064a\u0633\u0627\u0631 \u0648\u0623\u0646\u0634\u0626 \u0635\u0648\u0631\u062a\u0643 \u0628\u0646\u0641\u0633 \u0627\u0644\u0623\u0633\u0644\u0648\u0628 \u0628\u0636\u063a\u0637\u0629 \u0648\u0627\u062d\u062f\u0629 \u0645\u062c\u0627\u0646\u0627\u064b!  AI Portrait Template\u3001Gothic Portrait\u3001Dark Feminine\u3001Black Lace Veil\u3001Lace Shadow\u3001Cinematic Beauty\u3001Luxury Portrait\u3001Fine Art Photography\u3001AI Image Generator\u3001Free Template\u3001Trending Search\u3001TikTok Trend #capcutnow",
    "timestamp": "2026-06-25T10:40:18+00:00",
    "likes": 11414,
    "comments": 57,
    "shares": 6255,
    "views": 513567,
    "saves": 2015,
    "music": "original sound - user80276956658057",
    "audio_song": "original sound - user80276956658057",
    "audio_artist": "shine",
    "audio_id": "7655281114264668942",
    "audio_is_original": true,
    "engagement": 17726,
    "trendScore": 3.5,
    "velocity": 28216,
    "ageDays": 18.2,
    "source": "keyword:cinematic photography",
    "isNewAccount": true
  },
  {
    "platform": "tiktok",
    "account": "travelvlog018",
    "url": "https://www.tiktok.com/@travelvlog018/video/7656826913003965718",
    "thumbnail": "https://p16-common-sign.tiktokcdn-us.com/tos-no1a-p-0037-no/okDZdlSfRqEjKkF3BTDFALFoExfQgA8IwsBnQE~tplv-tiktokx-cropcenter:500:800.jpeg?biz_tag=musically_video.video_cover&dr=9638&idc=useast8&ps=13740610&refresh_token=b945a2dc&shcp=9b759fb9&shp=c1333099&t=4d5b0474&x-expires=1783976400&x-signature=%2F0rZABI8oOzqNd9qzJ4pl3lbJcw%3D",
    "video": "https://v16m.tiktokcdn-us.com/598ec709a9a761074ddcf133840cd36b/6a555914/video/tos/no1a/tos-no1a-ve-0068-no/o4cQoEFlCeqAp9OgOhEABFQERF6DYgLkpIftgM/?a=1233&bti=NTY6QGo0QHM6OjZANDQuYCMucCMxNDNg&&bt=860&ft=gKfIn8QLodzR12NvkwZZzIxRMQz_XF_45SY&mime_type=video_mp4&rc=OjwzPDU7OTdmNWZoNzVlOUBpamY5Nng5cnM7PDMzbzczNUAwXzQvMjVgNmIxXzMxMjYvYSNoLWlgMmRjMi5hLS1kMTFzcw%3D%3D&vvpl=1&l=20260713153008E95C0398557BBB07FC19&btag=e00088000",
    "carousel_urls": [],
    "format": "TikTok",
    "caption": "Here is how to get that high-end cinematic photos. \ud83c\udf08#photography #photographerlife #photographytips",
    "timestamp": "2026-06-29T14:39:09+00:00",
    "likes": 60892,
    "comments": 338,
    "shares": 1669,
    "views": 2112990,
    "saves": 6290,
    "music": "Faded (Dash Berlin Remix)",
    "audio_song": "Faded (Dash Berlin Remix)",
    "audio_artist": "Alan Walker",
    "audio_id": "6716968952053893122",
    "audio_is_original": false,
    "engagement": 62899,
    "trendScore": 3.0,
    "velocity": 150548,
    "ageDays": 14.0,
    "source": "keyword:cinematic photography",
    "isNewAccount": true
  },
  {
    "platform": "tiktok",
    "account": "aileenadalid",
    "url": "https://www.tiktok.com/@aileenadalid/video/7658342566659722503",
    "thumbnail": "https://p19-common-sign.tiktokcdn-us.com/tos-alisg-p-0037/oAg9APfIyfIXPAfSAfAQNySLIeC879igMG6SAX~tplv-tiktokx-origin.image?biz_tag=musically_video.video_cover&dr=8593&idc=useast5&ps=933b5bde&refresh_token=fd5bc814&s=SEARCH&sc=cover&shcp=c1333099&shp=d05b14bd&t=bacd0480&x-expires=1784041200&x-signature=O42F4GkYEoKE93m9dDEgnXsv9q4%3D",
    "video": "https://v16m.tiktokcdn-us.com/32587437d3a02ddb514401a844b350ca/6a555922/video/tos/alisg/tos-alisg-pve-0037c001/owRBDiBHQIev91Rmhqv4AbUH3kIEEQv1Bf55ig/?a=1233&bti=NEBzNTY6QGo6OjZALnAjNDQuYCMxNDNg&&bt=2303&ft=BIcq8V~3wUxl7K2gUtIvk84jWLpi0L~~QjKJfa5hgG0P3-I&mime_type=video_mp4&rc=PGZmZGlmOTZmaGY2ZzppZkBpanNwNW85cnh4PDMzODczNEA2LmFiNF4zNS0xYjNfNDEzYSNhczNnMmRrMDBhLS1kMTFzcw%3D%3D&vvpl=1&l=20260713153015F8627713AE64650B505C&btag=e00088000",
    "carousel_urls": [],
    "format": "TikTok",
    "caption": "I thought my DJI Osmo Pocket 3 was already enough for travel\u2026 until I tried the new DJI Pocket 4P. The biggest upgrade for me is the flexibility: wide shots for places, 60mm portraits for people, better handling in tricky light, 4K slow motion for travel B-roll, and D-Log 2 if you want more room to color grade \u2728 Basically, it still fits in a tiny setup, but the footage feels more polished and cinematic. For everyday clips, a phone is still convenient. But for travel shots I want to feel more intentional? This is the kind of camera I\u2019d reach for! Won\u2019t you agree?   \u26a0\ufe0fComment \u201c4P\u201d for more info on the newest DJI Pocket 4P! - - - #DJIPocket4P #vlogcamera #digitalcamera #pocketcamera #camerarecommendation",
    "timestamp": "2026-07-03T16:40:35+00:00",
    "likes": 7874,
    "comments": 34,
    "shares": 189,
    "views": 853635,
    "saves": 605,
    "music": "original sound - aileenadalid",
    "audio_song": "original sound - aileenadalid",
    "audio_artist": "Aileen Adalid",
    "audio_id": "7658342600717437717",
    "audio_is_original": true,
    "engagement": 8097,
    "trendScore": 0.9,
    "velocity": 85784,
    "ageDays": 10.0,
    "source": "keyword:cinematic b roll",
    "isNewAccount": true
  }
]